Workbook

Sheet All Disasters
A1: Disaster Row # | B1: Name | C1: Disaster Type | D1: Begin Date | E1: End Date | F1: CPI-Adjusted Cost ($M) | G1: Unadjusted Cost ($M) | H1: Deaths | I1: States | J1: Engines | K1: # Articles Found | L1: Avg Attribution Index
A2: 1 | B2: Southeast Winter Storm (January 2000) | C2: Winter Storm | D2: 20000121 | E2: 20000124 | F2: 1320.3 | G2: 706 | H2: 4 | I2: AL,FL,GA,KY,MS,NC,SC,TN,VA,WV | J2: 3,4,5,6,7,8,National | K2: =COUNTIF(Master!A$2:A$1695,A2) -> 1 | L2: =IFERROR(AVERAGEIFS(Master!P$2:P$1695,Master!A$2:A$1695,A2,Master!O$2:O$1695,"Relevant"),"")
A3: 2 | B3: Southern Severe Weather (March 2000) | C3: Severe Storm | D3: 20000328 | E3: 20000329 | F3: 1269.6 | G3: 690 | H3: 0 | I3: AL,AR,FL,GA,KY,LA,MS,NC,OK,SC,TN,TX,VA | J3: 13,14,15,3,4,5,6,7,8,National | K3: =COUNTIF(Master!A$2:A$1695,A3) -> 0 | L3: =IFERROR(AVERAGEIFS(Master!P$2:P$1695,Master!A$2:A$1695,A3,Master!O$2:O$1695,"Relevant"),"")
A4: 3 | B4: Western Fire Season (Spring-Summer 2000) | C4: Wildfire | D4: 20000301 | E4: 20000831 | F4: 1978 | G4: 1075 | H4: 0 | I4: AK,AZ,CA,CO,HI,ID,MT,NM,NV,OR,UT,WA,WY | J4: 15,16,17,18,National | K4: =COUNTIF(Master!A$2:A$1695,A4) -> 5 | L4: =IFERROR(AVERAGEIFS(Master!P$2:P$1695,Master!A$2:A$1695,A4,Master!O$2:O$1695,"Relevant"),"")
A5: 4 | B5: South Florida Flooding (October 2000) | C5: Flooding | D5: 20001003 | E5: 20001004 | F5: 1629 | G5: 900 | H5: 3 | I5: FL | J5: 3,4,5,6,National | K5: =COUNTIF(Master!A$2:A$1695,A5) -> 0 | L5: =IFERROR(AVERAGEIFS(Master!P$2:P$1695,Master!A$2:A$1695,A5,Master!O$2:O$1695,"Relevant"),"")
A6: 5 | B6: Western/Central/Southeast Drought/Heat Wave (Spring-Fall 2000) | C6: Drought | D6: 20000301 | E6: 20001130 | F6: 9344.8 | G6: 4997.2 | H6: 140 | I6: AK,AL,AZ,CA,CO,FL,GA,HI,IA,ID,IL,IN,KS,KY,MI,MN,MO,MS,MT,NC,ND,NE,NM,NV,OH,OK,OR,SC,SD,TN,TX,UT,VA,WA,WI,WV,WY | J6: 10,11,12,13,14,15,16,17,18,3,4,5,6,7,8,9,National | K6: =COUNTIF(Master!A$2:A$1695,A6) -> 1 | L6: =IFERROR(AVERAGEIFS(Master!P$2:P$1695,Master!A$2:A$1695,A6,Master!O$2:O$1695,"Relevant"),"")
A7: 6 | B7: Midwest/Ohio Valley Hail and Tornadoes (April 2001) | C7: Severe Storm | D7: 20010406 | E7: 20010411 | F7: 5508.7 | G7: 3094.8 | H7: 3 | I7: IA,IL,IN,KS,KY,MI,MN,MO,ND,NE,OH,SD,TN,WI,WV | J7: 10,11,12,13,3,4,5,6,7,8,9,National | K7: =COUNTIF(Master!A$2:A$1695,A7) -> 0 | L7: =IFERROR(AVERAGEIFS(Master!P$2:P$1695,Master!A$2:A$1695,A7,Master!O$2:O$1695,"Relevant"),"")
A8: 7 | B8: North Central Severe Weather (May 2001) | C8: Severe Storm | D8: 20010430 | E8: 20010501 | F8: 1194.3 | G8: 671 | H8: 0 | I8: IA,IL,IN,KS,MI,MN,MO,ND,NE,OH,SD,WI | J8: 10,11,12,13,8,9,National | K8: =COUNTIF(Master!A$2:A$1695,A8) -> 0 | L8: =IFERROR(AVERAGEIFS(Master!P$2:P$1695,Master!A$2:A$1695,A8,Master!O$2:O$1695,"Relevant"),"")
A9: 8 | B9: Tropical Storm Allison (June 2001) | C9: Tropical Cyclone | D9: 20010605 | E9: 20010617 | F9: 15084 | G9: 8522 | H9: 43 | I9: LA,TX | J9: 13,14,15,National | K9: =COUNTIF(Master!A$2:A$1695,A9) -> 3 | L9: =IFERROR(AVERAGEIFS(Master!P$2:P$1695,Master!A$2:A$1695,A9,Master!O$2:O$1695,"Relevant"),"")
A10: 9 | B10: Severe Storms and Tornadoes (April 2002) | C10: Severe Storm | D10: 20020427 | E10: 20020428 | F10: 3663.9 | G10: 2093.8 | H10: 7 | I10: NATIONAL | J10: National | K10: =COUNTIF(Master!A$2:A$1695,A10) -> 3 | L10: =IFERROR(AVERAGEIFS(Master!P$2:P$1695,Master!A$2:A$1695,A10,Master!O$2:O$1695,"Relevant"),"")
A11: 10 | B11: Hurricane Lili (October 2002) | C11: Tropical Cyclone | D11: 20020801 | E11: 20020805 | F11: 1932.9 | G11: 1104.5 | H11: 2 | I11: LA | J11: 13,14,15,National | K11: =COUNTIF(Master!A$2:A$1695,A11) -> 0 | L11: =IFERROR(AVERAGEIFS(Master!P$2:P$1695,Master!A$2:A$1695,A11,Master!O$2:O$1695,"Relevant"),"")
A12: 11 | B12: Tropical Storm Isidore (September 2002) | C12: Tropical Cyclone | D12: 20020925 | E12: 20020927 | F12: 2001 | G12: 1150 | H12: 5 | I12: AL,LA,MS | J12: 13,14,15,6,7,8,National | K12: =COUNTIF(Master!A$2:A$1695,A12) -> 4 | L12: =IFERROR(AVERAGEIFS(Master!P$2:P$1695,Master!A$2:A$1695,A12,Master!O$2:O$1695,"Relevant"),"")
A13: 12 | B13: Eastern Tornadoes and Severe Storms (November 2002) | C13: Severe Storm | D13: 20021109 | E13: 20021111 | F13: 1252.8 | G13: 720 | H13: 28 | I13: CT,DE,FL,GA,MA,MD,ME,NC,NH,NJ,NY,PA,RI,SC,VA,VT,WV | J13: 1,2,3,4,5,6,National | K13: =COUNTIF(Master!A$2:A$1695,A13) -> 1 | L13: =IFERROR(AVERAGEIFS(Master!P$2:P$1695,Master!A$2:A$1695,A13,Master!O$2:O$1695,"Relevant"),"")
... A314: 313 | B314: Southern/Eastern/Northwestern Drought and Heat Wave (2024) | C314: Drought | D314: 20240101 | E314: 20241231 | F314: 5417 | G314: 5311 | H314: 136 | I314: AL,AR,CT,DE,FL,GA,ID,KY,LA,MA,MD,ME,MS,MT,NC,NH,NJ,NY,OK,OR,PA,RI,SC,TN,TX,VA,VT,WA,WV | J314: 1,13,14,15,16,17,18,2,3,4,5,6,7,8,National | K314: =COUNTIF(Master!A$2:A$1695,A314) -> 22 | L314: =IFERROR(AVERAGEIFS(Master!P$2:P$1695,Master!A$2:A$1695,A314,Master!O$2:O$1695,"Relevant"),"")

Sheet Master
A1: Disaster Row # | B1: Article # | C1: Name | D1: Disaster Type | E1: Begin Date | F1: End Date | G1: CPI-Adjusted Cost ($M) | H1: Unadjusted Cost ($M) | I1: Deaths | J1: States | K1: Engines | L1: URL | M1: Title | N1: Snippet | O1: Relevance | P1: Attribution Index | Q1: National Newspaper | R1: Calibration Sample | S1: Full Article Text
A2: 1 | B2: 1 | C2: Southeast Winter Storm (January 2000) | D2: Winter Storm | E2: 20000121 | F2: 20000124 | G2: 1320.3 | H2: 706 | I2: 4 | J2: AL,FL,GA,KY,MS,NC,SC,TN,VA,WV | K2: 3,4,5,6,7,8,National | L2: https://www.nytimes.com/2000/01/24/us/500000-homes-left-dark-by-ice-storm-in-southeast.html | M2: 500000 Homes Left Dark By Ice Storm in Southeast | N2: Jan 24, 2000 ... Winter storm sweeps Southeast, from northeast Georgia to central ... 24, 2000, Section A, Page 12 of the National edition with the ... | Q2: =IF(SUMPRODUCT(--ISNUMBER(SEARCH('National Domains'!$A$2:$A$48,L2)))>0,"Yes","No") -> Yes | R2: =IF(COUNTIFS(Calibration!$A:$A,A2,Calibration!$B:$B,B2)>0,"Yes","No") -> Yes
A3: 3 | B3: 1 | C3: Western Fire Season (Spring-Summer 2000) | D3: Wildfire | E3: 20000301 | F3: 20000831 | G3: 1978 | H3: 1075 | I3: 0 | J3: AK,AZ,CA,CO,HI,ID,MT,NM,NV,OR,UT,WA,WY | K3: 15,16,17,18,National | L3: http://www.cnn.com/2000/US/08/13/wildfires.02/index.html | M3: Western wildfires finally lose ground - August 13, 2000 - CNN | N3: Aug 13, 2000 ... CNN.com · U.S. News ; Western wildfires finally lose ground. GALLERY. A cheatgrass fire in Nevada moves as fast as the wind will carry it -- ... | Q3: =IF(SUMPRODUCT(--ISNUMBER(SEARCH('National Domains'!$A$2:$A$48,L3)))>0,"Yes","No") -> Yes | R3: =IF(COUNTIFS(Calibration!$A:$A,A3,Calibration!$B:$B,B3)>0,"Yes","No") -> No
A4: 3 | B4: 2 | C4: Western Fire Season (Spring-Summer 2000) | D4: Wildfire | E4: 20000301 | F4: 20000831 | G4: 1978 | H4: 1075 | I4: 0 | J4: AK,AZ,CA,CO,HI,ID,MT,NM,NV,OR,UT,WA,WY | K4: 15,16,17,18,National | L4: http://www.cnn.com/2000/US/07/04/colorado.wildfires/index.html | M4: Two wildfires burn in Colorado - July 4, 2000 - CNN | N4: Jul 4, 2000 ... June 15, 2000. Wildfires rage in western United States June 14, 2000. Firefighters gain hold on Southern California wildfire. June 12, 2000 | Q4: =IF(SUMPRODUCT(--ISNUMBER(SEARCH('National Domains'!$A$2:$A$48,L4)))>0,"Yes","No") -> Yes | R4: =IF(COUNTIFS(Calibration!$A:$A,A4,Calibration!$B:$B,B4)>0,"Yes","No") -> No
A5: 3 | B5: 3 | C5: Western Fire Season (Spring-Summer 2000) | D5: Wildfire | E5: 20000301 | F5: 20000831 | G5: 1978 | H5: 1075 | I5: 0 | J5: AK,AZ,CA,CO,HI,ID,MT,NM,NV,OR,UT,WA,WY | K5: 15,16,17,18,National | L5: http://www.cnn.com/2000/US/09/12/wildfires.01/index.html | M5: West still on wildfire watch - September 12, 2000 - CNN | N5: Sep 12, 2000 ... The National Interagency Fire Center reported that several states, mostly in the West, have very high to extreme fire conditions -- Arizona, ... | Q5: =IF(SUMPRODUCT(--ISNUMBER(SEARCH('National Domains'!$A$2:$A$48,L5)))>0,"Yes","No") -> Yes | R5: =IF(COUNTIFS(Calibration!$A:$A,A5,Calibration!$B:$B,B5)>0,"Yes","No") -> No
A6: 3 | B6: 4 | C6: Western Fire Season (Spring-Summer 2000) | D6: Wildfire | E6: 20000301 | F6: 20000831 | G6: 1978 | H6: 1075 | I6: 0 | J6: AK,AZ,CA,CO,HI,ID,MT,NM,NV,OR,UT,WA,WY | K6: 15,16,17,18,National | L6: http://www.cnn.com/2000/NATURE/08/18/urban.interface/index.html | M6: Western wildfires often battled in the front yard - August 18, 2000 | N6: Aug 18, 2000 ... As the wildfires continue to burn in Montana's Bitteroot Valley, nearly a quarter of a million acres of the Bitteroot National Forest have ... | Q6: =IF(SUMPRODUCT(--ISNUMBER(SEARCH('National Domains'!$A$2:$A$48,L6)))>0,"Yes","No") -> Yes | R6: =IF(COUNTIFS(Calibration!$A:$A,A6,Calibration!$B:$B,B6)>0,"Yes","No") -> No
A7: 3 | B7: 5 | C7: Western Fire Season (Spring-Summer 2000) | D7: Wildfire | E7: 20000301 | F7: 20000831 | G7: 1978 | H7: 1075 | I7: 0 | J7: AK,AZ,CA,CO,HI,ID,MT,NM,NV,OR,UT,WA,WY | K7: 15,16,17,18,National | L7: http://www.cnn.com/2000/US/09/08/wildfires.02/index.html | M7: 'Good progress' against U.S. wildfires - September 8, 2000 - CNN | N7: Sep 8, 2000 ... By Jim Morris CNN.com Senior Writer. GALLERY. Click here for images of the ongoing fight against the wildfires. WEATHER FORECASTS. Idaho | Q7: =IF(SUMPRODUCT(--ISNUMBER(SEARCH('National Domains'!$A$2:$A$48,L7)))>0,"Yes","No") -> Yes | R7: =IF(COUNTIFS(Calibration!$A:$A,A7,Calibration!$B:$B,B7)>0,"Yes","No") -> No
A8: 5 | B8: 1 | C8: Western/Central/Southeast Drought/Heat Wave (Spring-Fall 2000) | D8: Drought | E8: 20000301 | F8: 20001130 | G8: 9344.8 | H8: 4997.2 | I8: 140 | J8: AK,AL,AZ,CA,CO,FL,GA,HI,IA,ID,IL,IN,KS,KY,MI,MN,MO,MS,MT,NC,ND,NE,NM,NV,OH,OK,OR,SC,SD,TN,TX,UT,VA,WA,WI,WV,WY | K8: 10,11,12,13,14,15,16,17,18,3,4,5,6,7,8,9,National | L8: https://www.baltimoresun.com/2000/03/14/drought-forecast-in-much-of-us-some-states-face-crisis-md-warned-to-expect-less-rain-than-usual/ | M8: Drought forecast in much of U.S.; Some states face crisis; Md ... | N8: Mar 14, 2000 ... These frequently produce heavy rains in the Northwest, drought in the Southeast and more tropical storms and hurricanes in the Atlantic Ocean. | Q8: =IF(SUMPRODUCT(--ISNUMBER(SEARCH('National Domains'!$A$2:$A$48,L8)))>0,"Yes","No") -> Yes | R8: =IF(COUNTIFS(Calibration!$A:$A,A8,Calibration!$B:$B,B8)>0,"Yes","No") -> No
A9: 8 | B9: 1 | C9: Tropical Storm Allison (June 2001) | D9: Tropical Cyclone | E9: 20010605 | F9: 20010617 | G9: 15084 | H9: 8522 | I9: 43 | J9: LA,TX | K9: 13,14,15,National | L9: https://www.chron.com/news/houston-texas/article/Tropical-Storm-Allison-takesHouston-Galveston-by-2046653.php | M9: Tropical Storm Allison takesHouston, Galveston by surprise - Chron | N9: Jun 5, 2001 ... The first named storm of the hurricane season, Tropical Storm Allison ... He is a proud native of South Africa, citizen of the United States and ... | Q9: =IF(SUMPRODUCT(--ISNUMBER(SEARCH('National Domains'!$A$2:$A$48,L9)))>0,"Yes","No") -> No | R9: =IF(COUNTIFS(Calibration!$A:$A,A9,Calibration!$B:$B,B9)>0,"Yes","No") -> No
A10: 8 | B10: 2 | C10: Tropical Storm Allison (June 2001) | D10: Tropical Cyclone | E10: 20010605 | F10: 20010617 | G10: 15084 | H10: 8522 | I10: 43 | J10: LA,TX | K10: 13,14,15,National | L10: https://www.chron.com/life/article/Fresh-news-Tropical-Storm-Allison-dumps-on-city-2048790.php | M10: Fresh news: Tropical Storm Allison dumps on city - Chron | N10: Jun 14, 2001 ... Tropical Storm Allison broke Houston's heart, but not its spirit. ... None of the hurricanes hit the United States. ... June 14, 2001. Chron ... | Q10: =IF(SUMPRODUCT(--ISNUMBER(SEARCH('National Domains'!$A$2:$A$48,L10)))>0,"Yes","No") -> No | R10: =IF(COUNTIFS(Calibration!$A:$A,A10,Calibration!$B:$B,B10)>0,"Yes","No") -> No
A11: 8 | B11: 3 | C11: Tropical Storm Allison (June 2001) | D11: Tropical Cyclone | E11: 20010605 | F11: 20010617 | G11: 15084 | H11: 8522 | I11: 43 | J11: LA,TX | K11: 13,14,15,National | L11: https://www.nytimes.com/2001/06/11/us/tropical-storm-leaves-16-dead-in-2-gulf-states.html | M11: Tropical Storm Leaves 16 Dead In 2 Gulf States - The New York Times | N11: Jun 11, 2001 ... ... Tropical Storm Allison, which left 15 people dead and about 10000 ... https://www.nytimes.com/2001/06/11/us/tropical-storm-leaves-16 ... | Q11: =IF(SUMPRODUCT(--ISNUMBER(SEARCH('National Domains'!$A$2:$A$48,L11)))>0,"Yes","No") -> Yes | R11: =IF(COUNTIFS(Calibration!$A:$A,A11,Calibration!$B:$B,B11)>0,"Yes","No") -> No
A12: 9 | B12: 1 | C12: Severe Storms and Tornadoes (April 2002) | D12: Severe Storm | E12: 20020427 | F12: 20020428 | G12: 3663.9 | H12: 2093.8 | I12: 7 | J12: NATIONAL | K12: National | L12: http://www.cnn.com/2002/WEATHER/04/28/storm.deaths/index.html | M12: Twisters leave at least 6 dead - April 29, 2002 - CNN | N12: Apr 29, 2002 ... The twister system in the Midwest killed three people in three states early Sunday, while three others died in Maryland when a tornado ... | Q12: =IF(SUMPRODUCT(--ISNUMBER(SEARCH('National Domains'!$A$2:$A$48,L12)))>0,"Yes","No") -> Yes | R12: =IF(COUNTIFS(Calibration!$A:$A,A12,Calibration!$B:$B,B12)>0,"Yes","No") -> No
A13: 9 | B13: 2 | C13: Severe Storms and Tornadoes (April 2002) | D13: Severe Storm | E13: 20020427 | F13: 20020428 | G13: 3663.9 | H13: 2093.8 | I13: 7 | J13: NATIONAL | K13: National | L13: http://www.cnn.com/2002/WEATHER/04/29/storm.deaths/index.html | M13: Killer tornado becomes one for the books in Maryland - April 29, 2002 | N13: Violent storms kill at least 6 in 4 states. April 29, 2002 Posted: 11:07 PM EDT (0307 GMT) ... "One of the strongest tornadoes ever to strike the state of ... | Q13: =IF(SUMPRODUCT(--ISNUMBER(SEARCH('National Domains'!$A$2:$A$48,L13)))>0,"Yes","No") -> Yes | R13: =IF(COUNTIFS(Calibration!$A:$A,A13,Calibration!$B:$B,B13)>0,"Yes","No") -> No
... A1695: 313 | B1695: 22 | C1695: Southern/Eastern/Northwestern Drought and Heat Wave (2024) | D1695: Drought | E1695: 20240101 | F1695: 20241231 | G1695: 5417 | H1695: 5311 | I1695: 136 | J1695: AL,AR,CT,DE,FL,GA,ID,KY,LA,MA,MD,ME,MS,MT,NC,NH,NJ,NY,OK,OR,PA,RI,SC,TN,TX,VA,VT,WA,WV | K1695: 1,13,14,15,16,17,18,2,3,4,5,6,7,8,National | L1695: https://www.washingtonpost.com/weather/2024/12/19/drought-southwest-rain-las-vegas/ | M1695: Drought deepens in the Southwest, driven by little rain and extreme ... | N1695: Dec 19, 2024 ... Drought is deepening in the Southwestern United States ... An extraordinary heat wave in October brought record temperatures to Phoenix for 21 ... | Q1695: =IF(SUMPRODUCT(--ISNUMBER(SEARCH('National Domains'!$A$2:$A$48,L1695)))>0,"Yes","No") -> Yes | R1695: =IF(COUNTIFS(Calibration!$A:$A,A1695,Calibration!$B:$B,B1695)>0,"Yes","No") -> No

Sheet Active
A1: Disaster Row # | B1: Article # | C1: Name | D1: Disaster Type | E1: Begin Date | F1: End Date | G1: CPI-Adjusted Cost ($M) | H1: Unadjusted Cost ($M) | I1: Deaths | J1: States | K1: Engines | L1: URL | M1: Title | N1: Snippet | O1: Relevance | P1: Attribution Index | Q1: National Newspaper | R1: Calibration Sample | S1: Full Article Text
A2: =_xlfn._xlws.FILTER(Master!A2:S1695,Master!O2:O1695="Relevant","No rows tagged as 'Relevant' yet") -> No rows tagged as 'Relevant' yet

Sheet Trash
A1: Disaster Row # | B1: Article # | C1: Name | D1: Disaster Type | E1: Begin Date | F1: End Date | G1: CPI-Adjusted Cost ($M) | H1: Unadjusted Cost ($M) | I1: Deaths | J1: States | K1: Engines | L1: URL | M1: Title | N1: Snippet | O1: Relevance | P1: Attribution Index | Q1: National Newspaper | R1: Calibration Sample | S1: Full Article Text
A2: =_xlfn._xlws.FILTER(Master!A2:S1695,Master!O2:O1695="Trash","No rows tagged as 'Trash' yet") -> No rows tagged as 'Trash' yet

Sheet National Domains
A1: Domain
A2: aim.org
A3: anavecianasuarez.com
A4: apnews.com
A5: baltimoresun.com
A6: baytobaynews.com
A7: bloggingawaydebt.com
A8: bostonglobe.com
A9: cleverdude.com
A10: cnn.com
A11: computerworld.com
A12: dailyvoice.com
... A48: wvnews.com

Sheet Calibration
A1: Disaster Row # | B1: Article # | C1: Name | D1: Disaster Type | E1: Begin Date | F1: End Date | G1: States | H1: URL | I1: Title | J1: Snippet | K1: Full Article Text | L1: Human Relevance | M1: Human Attribution Category | N1: Human Attribution Score | O1: Human D-Subtype | P1: Human Contested | Q1: LLM Relevance | R1: LLM Attribution Category | S1: LLM Attribution Score | T1: LLM D-Subtype | U1: LLM Contested | V1: Notes
A2: 1 | B2: 1 | C2: Southeast Winter Storm (January 2000) | D2: Winter Storm | E2: 20000121 | F2: 20000124 | G2: AL,FL,GA,KY,MS,NC,SC,TN,VA,WV | H2: https://www.nytimes.com/2000/01/24/us/500000-homes-left-dark-by-ice-storm-in-southeast.html | I2: 500000 Homes Left Dark By Ice Storm in Southeast | J2: Jan 24, 2000 ... Winter storm sweeps Southeast, from northeast Georgia to central ... 24, 2000, Section A, Page 12 of the National edition with the ... | N2: =IF(M2="","",IF(M2="A",1,IF(M2="B",0.5,IF(M2="C",0,IF(M2="D",-1,IF(M2="E",0,"")))))) | S2: =IF(R2="","",IF(R2="A",1,IF(R2="B",0.5,IF(R2="C",0,IF(R2="D",-1,IF(R2="E",0,""))))))
A3: 11 | B3: 4 | C3: Tropical Storm Isidore (September 2002) | D3: Tropical Cyclone | E3: 20020925 | F3: 20020927 | G3: AL,LA,MS | H3: https://www.washingtonpost.com/archive/politics/2002/10/03/500000-ordered-to-flee-as-lili-nears-gulf-coast/858d3b42-aa47-435e-8a0e-ebc69afd9872/ | I3: 500000 Ordered to Flee As Lili Nears Gulf Coast | J3: Oct 2, 2002 ... It is potentially far more destructive than last week's Tropical Storm Isidore. Forecasters upgraded Lili to a Category 4 hurricane, the ... | K3: NEW ORLEANS, Oct. 2 -- -- Nearly 500,000 residents of coastal Louisiana and Texas were told to evacuate today as the Gulf Coast braced for Hurricane Lili, a storm intensifying in strength as it aimed for a region still recovering from a tropical storm a week ago. Lili was surging up from the Caribbean today with 140-mph winds and was expected to make landfall Thursday morning. It is potentially far more destructive than last week's Tropical Storm Isidore. Forecasters upgraded Lili to a Category 4 hurricane, the second most powerful. It has already killed seven on Jamaica and St. Vincent and forced thousands of Cubans to flee their homes. "This has the potential to kill hundreds," said Max Mayfield, director of the National Hurricane Center in Miami. "Damage is going to be extensive. You better not get too close to this one." In the coastal area straddling Texas and Louisiana, weary residents still cleaning up from last week's $100 million in damage boarded up windows, sand-bagged doors, and braced for potential devastation. A hurricane warning extended from east of High Island, Tex., to the mouth of the Mississippi River in southeastern Louisiana. "We're getting ready for the real thing," said Ruth Fontenot, the mayor of New Iberia, a Cajun town in Louisiana's rice and sugar region, and a near bull's-eye in the storm's projected path. "It's increasingly gloomy in New Iberia." Fearful of a "catastrophic" potential 20-foot storm surge that would inundate the picturesque regional capital 140 miles west of New Orleans, she had just ordered the evacuation of all 35,000 citizens, and sent her own children out of town. New Iberia is only 10 miles from Vermilion Bay, which opens into the Gulf of Mexico. "The message I've been sending out is, 'Leave,' " Fontenot said. New Orleans, at the storm's projected eastern edge, remained calm today though area schools were to be closed Thursday, City Hall was ordered shut except for "essential" personnel, and Mayor Ray Nagin urged residents to stay close to home. "This is a very, very potent storm," Nagin said. Wind gusts of 30 to 40 mph were buffeting the city tonight. New Orleans was battered by heavy rain last week and suffered some flooding but quickly recovered thanks to its battery of 22 heavy pumping stations. States of emergency were declared in Louisiana and Texas. In Texas, officials urged 250,000 people in the Beaumont-Port Arthur area and 80,000 in Orange County to go inland, including 3,000 prisoners who were moved to jails away from the coast. Coastal ports in Louisiana that handle substantial percentages of the nation's oil imports were shut down. NASA's Mission Control in Houston was shut down, postponing today's scheduled space shuttle launch at Cape Canaveral, about 900 miles away. It was the first time in 41 years of manned space flights that bad weather in Houston prevented a Florida launch. In wild and marshy Cameron Parish, on Louisiana's sparsely populated southwestern coast, nearly the entire population of 10,000 people had been evacuated by this afternoon. "We're definitely going to get something out of this one," said sheriff's deputy Ed Racca. But he said residents had remained calm through the first evacuation in 10 years. "The older folks are used to this kind of stuff," Racca said. Roads north of Cameron Parish were reported clogged with heavy traffic. In Creole, a few miles from the gulf, "Everyone's pretty much gone," Michelle Trahan said this afternoon. "It's very quiet, very deserted," she said. She was waiting for her husband, a Cameron Parish police juror (county commissioner) to finish boarding up houses, before leaving herself. In New Iberia, residents and city workers worked feverishly throughout the afternoon at sand-bagging doors. "We're going to make it," said Fontenot, the mayor. "It's just not going to be very pleasant." | L3: Trash | N3: =IF(M3="","",IF(M3="A",1,IF(M3="B",0.5,IF(M3="C",0,IF(M3="D",-1,IF(M3="E",0,"")))))) | S3: =IF(R3="","",IF(R3="A",1,IF(R3="B",0.5,IF(R3="C",0,IF(R3="D",-1,IF(R3="E",0,""))))))
A4: 12 | B4: 1 | C4: Eastern Tornadoes and Severe Storms (November 2002) | D4: Severe Storm | E4: 20021109 | F4: 20021111 | G4: CT,DE,FL,GA,MA,MD,ME,NC,NH,NJ,NY,PA,RI,SC,VA,VT,WV | H4: https://www.capecodtimes.com/story/news/2002/11/12/deadly-winds/50957526007/ | I4: Deadly winds - Cape Cod Times | J4: Nov 12, 2002 ... Residents of Mossy Grove, Tenn., sift through the wreckage left by a tornado. Savage rash of twisters slices across U.S., killing at least 35 ... | K4: Savage rash of twisters slices across U.S., killing at least 35 Tennessee, Alabama worst hit search for missing continues Violent storms, including more than 70 tornadoes, blew across the nation early yesterday, slashing through small towns, splintering buildings and trees, twirling semi-trucks and cars and killing at least 35 people in a swath that stretched from the Gulf of Mexico to the Great Lakes. Starting late Saturday, the storms' fury mounted and swept from Louisiana, through Mississippi, Alabama, Tennessee and Ohio into Pennsylvania. early yesterday morning, the winds had demolished more than half of the two dozen houses that made up Mossy Grove, Tenn., a hamlet 40 miles west of Knoxville. Officials estimated more than a third of the structures were destroyed in Carbon Hill, Ala., a town of 2,071 people northwest of Birmingham. The deaths were most numerous in Tennessee where 16 people died, including seven in Mossy Grove. Another 12 were killed in Alabama, including seven in Carbon Hill. Five died in Ohio and one each in Mississippi and Pennsylvania. More than 200 people were injured. It was the deadliest swarm of tornadoes the nation has suffered since 1999 when at least 70 twisters killed more than 45 people over two days in Kansas and Oklahoma. Some places had only a few minutes' notice before the tornadoes swirled into town. In Van Wert, Ohio, that was just enough time to save dozens of people at the local movie theater. A manager heard a weather report on the radio as showings of "The Santa Clause 2" and "My Big Fat Greek Wedding" were ending and herded customers into hallways and restrooms - three cars blew into the theater and the roof collapsed on the blue-cushioned seats. "It wiped out three factories," said Larry Blakeley, 53, who lives about two miles from where the tornado touched down in Van Wert. "We had high winds and lightning. There are police cars and National Guard and you can't get close to where it happened." Radio pleas to the missingThe hardest-hit section in Tennessee included a five-mile stretch of Morgan County, which includes Mossy Grove. Rescuers spent yesterday combing through the wreckage. As the day ended, dozens of people were still missing. Local radio stations read the names of the missing over the airways and asked them to contact authorities if they heard their names. In some areas, phone calls on the lines that were working were so jammed that calls were not going through. Authorities were confident most people had fled their homes to safet would be accounted for soon. Still, the search was complicated by the devastation. "Emergency crews are out searching for people," said Amy Smith, a police dispatcher in nearby Oliver Springs. But she added, "The phone lines are down. They're without electric. It's going to be that way for a while." Officials from the Red Cross and emergency management teams spread out to assess the damage, and to provide those left homeless with food and shelter. In Alabama, Gov. Don Siegelman said it would take residents a long time to recover. "It's like somebody wrapped up sticks of dynamite and just blew these homes into little tiny pieces," Siegelman told reporters as he toured affected areas. "Clearly we've got to get money to these communities. But it's not so much the financial help at this point but the spiritual help that they need. We're going to do everything we can to get their lives, their homes back together." Winds hit an estimated 140 mph in Tennessee with torrential rain and golf-ball-size hail. The volatile weather was caused by unseasonably high temperatures, followed by a cold front pushing down from the north, creating optimal conditions for tornadoes, said Mark Linhares, a National Weather Service meteorologist based in Birmingham. Rare widespread twistersThe breadth of the storms was reminiscent of a similar tornado outbreak in November 1992 when a string of tornadoes sprang up in Texas and moved northeast. Ninety-four tornadoes resulted and 26 people were killed, 15 of them in Mississippi. But such widespread outbreaks are not common. In Alabama, nine people died in Walker County as a line of thunderstorms packing high winds and spinning off tornadoes rolled through the northern part of the state. In Georgia, heavy damage was reported near the town of Tate, about 45 miles north of Atlanta. In Tennessee, the tornadoes came in two waves. Late Saturda early Sunday, twisters skipped across western and middle Tennessee, killing three people. On Sunday night another line of storms crossed the state - this time south and east of Nashville. Two people, including a 10-year-old boy, were killed and 15 people were injured in Coffee County when two mobile home parks, three houses and a church were damaged near Manchester, about 60 miles southeast of Nashville, on Sunday night. | L4: Relevant | M4: C | N4: =IF(M4="","",IF(M4="A",1,IF(M4="B",0.5,IF(M4="C",0,IF(M4="D",-1,IF(M4="E",0,"")))))) -> 0 | S4: =IF(R4="","",IF(R4="A",1,IF(R4="B",0.5,IF(R4="C",0,IF(R4="D",-1,IF(R4="E",0,""))))))
A5: 14 | B5: 1 | C5: U.S. Drought (Spring-Fall 2002) | D5: Drought | E5: 20020301 | F5: 20021130 | G5: NATIONAL | H5: https://www.cnn.com/2002/WEATHER/07/22/us.drought/index.html | I5: Far-reaching drought chokes much of U.S. - July 22, 2002 - CNN | J5: Jul 22, 2002 ... The last major drought in the United States occurred in the late 1980s and had an estimated economic impact of nearly $40 billion. The ... | K5: (CNN) -- Four years without adequate rainfall have left a broad quilt of browned lawns, withered crops and scorched forests across much of the United States. But for Jeff Tranel, an agriculture and business economist with the Colorado State University extension service, it's what's not there that indicates how tough things are. "I'm out in the country quite a bit, and there are very few cows left," Tranel said recently. "In one county, Huerfano County, the 1997 census of agriculture data showed 28,000 beef cows in that county. A month ago, talking to ranchers, they said if you could find 1,000 to 5,000 cows, you would be lucky." The disappearance of thousands of cows from the heart of cattle country is a symptom of the severe drought that has gripped most of the West and much of the Southeast for four years. With nearly half the continental United States suffering from extremely dry conditions, some observers say it's the worst dry spell the country has seen in a generation -- perhaps two. "This drought is widespread and pretty intense over some large areas that rival those of the '50s," said Mark Svoboda, a climatologist at the National Drought Mitigation Center in Lincoln, Nebraska. "What we haven't seen maybe is the long-term heat, year after year after year, that we saw in the '30s." The effects have been seen most dramatically in Colorado, New Mexico and Arizona, where kiln-dry timberland exploded into a string of wildfires. More than 3.2 million acres have been burned this year, roughly twice the 10-year average, federal fire officials report. The U.S. Department of Agriculture has declared the entire state of Utah and numerous counties in Colorado, California, New Mexico and Arizona agricultural disaster areas, making farmers and ranchers in those regions eligible for federal emergency loans. The department also has opened millions of acres across 18 states from its Conservation Reserve Program for grazing and hay harvesting as ranchers have been forced to sell entire herds of cattle at a loss rather than keep them on drought-stricken pastureland. The last major drought in the United States occurred in the late 1980s and had an estimated economic impact of nearly $40 billion. The economic impact of the current drought differs among regions and sectors, Svoboda said, "but I think it's safe to say when it's all said and done, this one is going to be right up there. When we start looking at all the impacts, it's going to be in the billions of dollars." After years of drought in the Southwest and the Rockies, the High Plains states are starting to feel the pinch as well. In South Dakota, rainfall is about half of normal for much of the state, said Michael Held, administrative director for the South Dakota Farm Bureau. "In the central third of the state, most of the crops -- wheat as well as corn and soybeans -- have been severely damaged to completely ruined," he said. The drought is also causing problems for some of the fastest-growing cities in the increasingly urbanized Sunbelt, from Atlanta to Albuquerque. In New Mexico and southwestern Texas, only about 2 percent of the water that normally flows into Rio Grande has reached the river this year, said Barry Wirth, a spokesman for the U.S. Bureau of Reclamation. Along the Colorado River, which feeds some of the West's biggest cities -- including Las Vegas, Phoenix and Los Angeles -- water levels in major reservoirs like Lake Powell and Lake Mead are 50 to 60 feet below normal, Wirth said." It appears that we are on track right now to be equal to or worse than 1977, which was the worst drought year on record since Lake Powell was created. So we are in pretty stricken shape right now," he said. Residents of many of these cities are struggling with restrictions on water use even as more and more people are moving in. In Georgia, all 15 counties in metropolitan Atlanta are under water restrictions that allow outdoor watering only from 10 p.m. to 10 a.m. on alternate days. Lake Lanier, the major source of water for the area's nearly 4 million people, has been down as low as 12 feet below full pool in recent years: It is currently about 7 feet below normal. "We're only releasing the minimum flows necessary to preserve water quality in the system and water supply where needed," said Pat Robbins, a spokesman for the Army Corps of Engineers. "In other words, we've got it down to the absolute minimum that we can do, but we've got to maintain water quality and supply where it's needed." In Denver, city officials patrol enforce limits that allow homeowners to water lawns only every third day. Penalties range from a warning for first offenders to a $250 fine and the ultimate sanction -- having water cut off. "Our major job is to educate our customers on what they need to do," said Robert Trujillo, a member of the city's "Sod Squad." "Mostly, people understand. I haven't had anyone get really angry with me." The prospects for the future are uncertain. What forecasters are banking on to relieve the drought is the development of the recurring Pacific weather system known as El Nino. Scientists announced earlier this month that the phenomenon -- an above-average warming of eastern Pacific waters that typically occurs every four to five years -- should ease drought conditions in the Southeast and give the northern United States a mild winter. But continued concern can be seen in the picturesque snows atop the peaks of the Rockies. Mountain snowpacks serve as natural reservoirs that provide much of the next season's water supply for the West -- are currently between 25 percent to 40 percent of what observers consider normal, Svoboda said. "What's going be the real kicker is what happens this winter," Svoboda said. "Is this El Nino going to develop? It looks like it is, but is it going to be very strong? No, it doesn't look like it's going to be very strong. I think the jury's still out as to how beneficial this El Nino is going to be." The drought patrol, also known as the "Sod Squad," seeks out violations of water restrictions in Denver. | L5: Relevant | M5: C | N5: =IF(M5="","",IF(M5="A",1,IF(M5="B",0.5,IF(M5="C",0,IF(M5="D",-1,IF(M5="E",0,"")))))) -> 0 | S5: =IF(R5="","",IF(R5="A",1,IF(R5="B",0.5,IF(R5="C",0,IF(R5="D",-1,IF(R5="E",0,""))))))
A6: 20 | B6: 6 | C6: California Wildfires (Fall 2003) | D6: Wildfire | E6: 20030901 | F6: 20031130 | G6: CA | H6: https://www.latimes.com/archives/la-xpm-2003-oct-31-me-main31-story.html | I6: Weather Cools Wildfires' Fury - Los Angeles Times | J6: Oct 31, 2003 ... Northridge earthquake -- An article in Friday's Section A about the Southern California wildfires gave the wrong date for the Northridge ... | K6: A cloud bank carried welcome Pacific moisture to Southern California’s mountains Thursday, bringing badly needed relief to firefighters battling twin foes of fire and fatigue. Six fires, by some measures the most devastating in California history, continued to burn out of control in Los Angeles, Ventura, San Bernardino and San Diego counties. But the most dangerous of them appeared to be moving away from any towns, and there was a sense on the front lines that the worst may have passed. “This weather is so bizarre,” said Rancho Santa Fe Fire Department Capt. Gary Snavely, who was deployed to save the San Diego mountain town of Julian. “This town is threatened and on the brink of burning yesterday. And now it’s raining.” Julian, a historic gold mining town, appeared to have been spared, as was most of Lake Arrowhead. Fires were beaten back from communities in Ventura and northern Los Angeles counties. Still, there were new losses Thursday, including most of the community of Harrison Park in San Diego County. And any relief came tinged with an awareness that nature is unpredictable and the fires could yet be re-stoked by a change in winds. “I’m still very concerned,” Deputy Incident Cmdr. Donald Feser of the U.S. Forest Service said as he helped oversee the battle against the Old fire. That blaze had turned away from Arrowhead but still threatened the San Bernardino Mountain resort of Big Bear. “This fire still has a tremendous amount of potential.” Six days after the fires turned catastrophic, the California Department of Forestry and Fire Protection said this had become the worst wildfire season in the state since record-keeping began in the early 20th century. As of Wednesday, 959,955 acres had burned statewide, two-thirds in the past week in Southern California. The previous record was in 1987, when 873,000 acres burned. “We are nowhere near out of the fire season yet,” noted department spokeswoman Karen Terrill, “so it’s very likely we’ll pass the million-acre mark.” This week’s fires have been blamed for 20 deaths, including one firefighter, and the loss of at least 2,612 homes. They have scorched an estimated 745,000 acres, an area larger than Rhode Island. Losses have been estimated at more than $2 billion. “This will be the most expensive natural disaster the state has ever incurred,” Gov. Gray Davis said Thursday after an aerial tour of the devastation. “It will be the most expensive, the most severe and the longest in duration.” Despite Davis’ words, it seemed unlikely that the fires could approach the $20-billion cost of the 1993 Northridge earthquake, or the devastation of the 1906 San Francisco earthquake. Twenty-five people died and about 3,000 homes were destroyed in a much smaller area in the 1991 Oakland Hills fire. On Thursday afternoon, Gov.-elect Arnold Schwarzenegger took an hourlong helicopter tour of burned sections of the San Bernardino National Forest. Afterward, sporting a yellow CDF jacket, Schwarzenegger said he was impressed with the “incredible coordination of how this was planned. They knew this was going to happen if the forest was not cleaned up. If not for that ... many more families would not have their homes.” Schwarzenegger said he and Davis will meet today to discuss the devastation, and might fly over damaged areas together. Schwarzenegger earned a roar of applause from the roughly 1,000 assembled fire personnel when he praised their efforts, particularly in evacuating thousands of people from isolated mountain areas. “I play heroes in the movies,” he said. “These firefighters are the true heroes.” For the thousands of firefighters who have been deployed against the threat, many of them around the clock, the past week has been filled with danger, frustration, awe-inspiring spectacle, heartache and, ultimately, utter exhaustion. By Thursday, the ordeal was taking its toll. Allan Lee, 40, a Rancho Cucamonga firefighter, came down from the mountains Thursday morning after working on the Old fire in San Bernardino County since Saturday and watching hundreds of homes burn. Hungry and homesick, a cell phone call to his wife and two children brought his emotions welling to the surface. “I’m really tired,” he said, turning away and fighting back tears after hanging up the phone. “I just miss home.” San Diego The town of Julian, site of one of the most dramatic stands by firefighters, was deserted Thursday except for a dozen firetrucks parked on the main street. In front of the town hall, an American flag flew at half-staff in honor of the firefighter who died Wednesday defending the town. Two others injured in that battle were released from the hospital Thursday but a third remained in critical condition. The Cedar fire reached within 2 1/2 miles of downtown Wednesday, and spot fires licked within 300 yards. By Thursday, though, the fire was obscured by a haze of fog, mist and shifting smoke. Fire Capt. Ken Hale of the California Department of Forestry sat in his truck, exhausted, monitoring radio communications. Hale said firefighters were flanking the fire on its north and south sides in an attempt to narrow it until the two flanks meet. Hale said the main body of the fire was 25 miles wide. By Thursday night, the fire was 38% contained. The Cedar fire has been the largest in California’s recorded history, stretching over 272,318 acres from the outskirts of San Diego into the rugged terrain of the Cleveland National Forest. To attack it, firefighters have created fire breaks out of roads and bulldozed lines in the brush. But the steep, scruffy terrain made the effort difficult. It could be days before firefighters manage to narrow down the head of the fire significantly, Hale said. Meanwhile, he said, winds are expected to continue out of the west, pushing the fire to the east for the next two days. Little lies in that direction but hills and desert. The desert should serve as a natural fire break and could be where the fire finally dies. It remained dangerous Thursday. While firefighters managed to save Julian, a popular weekend destination for San Diegans, several small neighborhoods were badly damaged. The worst hit was Harrison Park, about five miles south of Julian, where at least 15 of approximately 20 homes were destroyed. “It just got nuked last night,” said Hale. Little that resembled an intact community remained in Harrison Park, which is nestled in a valley between steep hills. Trees were burned to skeletons. Homes were reduced to smoldering ruins. Chimneys stood near burnt-out truck and cars. Larry Cooke, 61, a retired fire captain with the San Diego City Fire Department, showed up to survey the destruction of his vacation cabin. The bed of his big green pickup truck contained the twisted remains of an antique cooking stove and kerosene lamps. “When I rebuild, I’ll put those in there just to remind me,” Cooke said as he chomped on an unlit cigar. He said he and his wife had been planning to fix up the cabin, which had been in his family for more than 75 years. “Well,” Cooke said, “now we won’t have any arguments on how to remodel. We have to start from scratch.” San Bernardino Two fronts of the Old fire continued to burn east of Lake Arrowhead after destroying an estimated 350 homes in the lakeside community of Cedar Glen. One was on the western edge of Big Bear Valley, near the Big Bear dam. The second was to the southwest near Keller Peak. As a layer of fog and mist moved into the area, accompanied by temperatures that cooled all the way down to the 40s, the fire slowed to a crawl. “This is the Pacific Ocean lying over our heads right now,” said Pete Dennen, the San Bernardino Fire Department division chief in charge of the Big Bear area. Still, Dennen warned against complacency. Wind gusts of up to 50 mph were blowing the fire northeastward, in a mostly harmless direction. But the blaze has mocked earlier predictions, along with efforts to contain it. “This fire can do anything,” Dennen said. “We’re just lucky, I’ll be the first to tell you.” In the 24 hours leading up to Thursday afternoon, fire crews bulldozed 20 miles of fire break between Big Bear and Highway 38, according to Feser, the Forest Service official. “The question is, ‘What would it take to put this fire out?’ ” Feser said. “I would say it would take a period of several weeks with at least three inches of rain.” Still, fire officials seemed pleased at the end of the day. A voluntary evacuation order was lifted in the high desert community of Lucerne Valley, which lies below Big Bear, as authorities became less concerned that the fire would charge down the north slope of the mountains. Although a cloud of smoke and fog hung over Big Bear, the unscathed forest areas to the east enjoyed a crystal-clear, smoke-free autumn day. The oak trees and chaparral were green and gold beneath a crisp blue sky, up to the point where Highway 38 wound around a mountain and back into the smudgy gray haze of the fire. On the eastern shore of Arrowhead, the community of Cedar Glen was a burned-out ghost town, the result of the fire that blew through on Wednesday. Falling trees and limbs, emerging out of the fog, posed a hazard to emergency crews, as did downed power lines. So hot were the flames that little silver streams marked the spots where aluminum window frames had melted. All was not devastation, however. Alan Wheeler returned to his wood-paneled split-level home in lower Cedar Glen, relieved to find the structure intact -- only 1,000 feet from where the fire tore its way through Hooks Creek late Wednesday afternoon. “I just can’t believe I’m standing in my house,” said Wheeler, a construction worker who has lived in the Arrowhead area for 29 years. “Yesterday I wouldn’t have given a plugged nickel for Cedar Glen or Arrowhead.” Wheeler said the first evacuation order came Saturday night, but he and his wife, Carolyn, decided to wait for the fire, confident that they could escape on Highway 173, which runs downhill into Hesperia. Finally, on Tuesday, they drove halfway down the mountains with two neighboring families to stay at a campground above the last checkpoint. Although the Wheelers returned home Thursday afternoon, Alan Wheeler said he was not going to unpack until the last hotspots around upper Cedar Glen were extinguished, and he was also not going to leave, even though supplies were limited to a single market and the weather had turned freezing cold. He said he would turn on his gas stove for heat through the night. “I thought about lighting a fire in the fireplace, he said. “But I don’t think that’d be a very good idea right now.” Ventura/Los Angeles The front lines of the 115,920-acre Simi Valley fire remained near the Stevenson Ranch subdivision in Los Angeles County, according to Ventura County Fire Department spokesman John Wade. Numerous bulldozer and hand crews worked to keep the flames from advancing north of Interstate 5. A reduction in winds and the cooler temperatures helped the firefighting effort. Wade said no homes had been lost in Stevenson Ranch. In Ventura County, “we don’t have any critical areas that are posing an immediate threat to any homes,” said Wade, a veteran firefighter who officially retired on Monday after nearly 38 years, but has remained at the fire base camp to lend a hand. Maintenance of the Simi fire in this area has turned to the monitoring of hot spots and continuing to build nearly 100 miles of containment line around the blaze. So far, containment is estimated at 60% and officials predict the job will be finished before Wednesday. “There’s still a lot of hard, dirty, cruddy work to be done,” Wade said. “This is when it becomes less exciting.” Near Fillmore, crews continued to battle a 63,719-acre fire burning north and northwest into the Los Padres National Forest. Hand crews and air tankers kept at the fire, which began a week ago and has been difficult to attack because it is burning in steep terrain and thick vegetation that in some areas has not burned since 1917, a Forest Service official said. Although the fire continued to spread westward within the national forest, officials said there was no imminent threat to the cities of Santa Paula, Fillmore or Ojai. | L6: Relevant | M6: C | N6: =IF(M6="","",IF(M6="A",1,IF(M6="B",0.5,IF(M6="C",0,IF(M6="D",-1,IF(M6="E",0,"")))))) -> 0 | S6: =IF(R6="","",IF(R6="A",1,IF(R6="B",0.5,IF(R6="C",0,IF(R6="D",-1,IF(R6="E",0,""))))))
A7: 27 | B7: 2 | C7: Hurricane Jeanne (September 2004) | D7: Tropical Cyclone | E7: 20040915 | F7: 20040929 | G7: FL | H7: http://www.cnn.com/2004/WEATHER/09/27/hurricane.jeanne/index.html | I7: Relief pours in as Jeanne moves north - Sep 27, 2004 - CNN | J7: Sep 27, 2004 ... A look back: Four hurricanes slam Florida in the state's worst-ever storm season. ... Scenes of Hurricane Jeanne pounding the Florida coast. | K7: TALLAHASSEE, Florida (CNN) -- Emergency officials in Florida shifted their focus from search and rescue to relief efforts Monday after Hurricane Jeanne cut a destructive path through the state. Florida Secretary of Health John Agwunobi said trucks carrying water, ice and other essentials were making their way to areas hardest hit. As of 5 p.m. ET, Jeanne had been downgraded to a tropical depression and its remnants were moving north-northeast through Georgia at about 13 mph with maximum sustained winds of 35 mph -- centered about 15 miles east-northeast of Macon. At least six people died in Florida as a result of the storm, state law enforcement officials said, and about 2.6 million customers were without power, said Secretary of Environmental Protection Colleen Castille. The storm made landfall late Saturday with 120 mph winds near the southern end of Hutchinson Island, five miles southeast of Stuart on Florida's east coast, near where Hurricane Frances came ashore September 5. It collapsed beachfront homes and ripped off roofs on a barrier island near Vero Beach in Indian River County. Concrete utility polls snapped at their bases, leaving power lines in the streets. In Melbourne, traffic was at a near standstill as residents who evacuated tried to return to their homes. City Manager Jack Schlukebier estimated that several hundred homes were damaged. About 75 percent of Melbourne residents were without power; at least 2,500 people remained in shelters, local officials said. Stuart Mayor Jeff Krauskopf said the biggest problem appeared to be roof damage. "Frances took out all the vegetation. Then when Jeanne came through, it got most of the roofs. Commercial [buildings] have had their roofs ripped off and they are being saturated with water," Krauskopf said. One of the major problems, Florida officials said, was flooding. Osceola County officials said they got 20 inches of rain as the storm passed, inundating areas that already were flooded from previous storms. Jeanne was the fourth hurricane to hit Florida in the past six weeks. "The resiliency of this state is awesome. While we're strained in terms of the resources of our state right now, we're unbowed," Gov. Jeb Bush told reporters during a visit to Pensacola, the Panhandle city that was hard hit by Hurricane Ivan nearly two weeks ago. President Bush declared Florida a major disaster area, making way for additional federal aid to supplement the state's recovery efforts. Risk Management Solutions, a catastrophe-modeling firm that works for the insurance industry, estimated Sunday that Jeanne could cause between $4 billion and $8 billion in insured losses in the United States. (Full story) State of emergency Jeanne was expected to turn to the northeast within 24 hours, the hurricane center said. Rainfall of 3 to 5 inches with isolated higher amounts can be expected along its path through Tuesday. The center warned of possible tornadoes from extreme eastern Georgia northeast through the Carolinas. Flood watches and warnings were in effect for portions of Georgia, South Carolina, North Carolina and Virginia. Valdosta in southern Georgia reported more than 5 inches of rain Monday. Georgia Gov. Sonny Perdue declared a state of emergency. Schools systems from Savannah to Augusta and west to Macon canceled classes. Thousands of airline passengers were stranded at Atlanta's Hartsfield-Jackson International Airport because Florida airports were closed or traffic was backed up. A group of nurses trying to travel home to the Tampa area was told they would probably be stuck in Atlanta for at least three days. Deadly wind and rain The Florida Highway Patrol said a man and woman from Boynton Beach drowned in a 40-foot-deep man-made lake in Deerfield Beach when their SUV left the Sawgrass Expressway and plunged into the water. Lt. Pat Santangelo, a spokesman for the Florida Highway Patrol, said the accident occurred Saturday night as the area was buffeted by high winds and driving rain. A tree along the St. Johns River fell late Sunday afternoon, killing a 15-year-old boy who was in his back yard with a friend, said Mary Justino, spokeswoman for the Clay County Sheriff's Department. She said the other teen was hurt, but the injuries weren't life-threatening. Elsewhere Sunday, a couple discovered a pickup in a deep drainage ditch in Palm Bay south of Melbourne, and its occupant had drowned, said police spokesman Barney Weiss. He said the man apparently drove into the flooded ditch by mistake. In Miami, authorities said a man was electrocuted when he touched a downed power line, and in Brevard County, the sheriff's office said a 60-year-old man was found dead in his flooded home after a hurricane party. Haiti death toll climbs Jeanne now is blamed for 1,330 deaths in Haiti, and 1,056 people have been reported missing. Haitian officials said Monday that almost 300,000 people had homes damaged or destroyed in the storm, which swept across the country September 18. Dieufort Deslorges, the head of the disaster relief section of the Haitian Department of Civil Protection, said 2,601 people were injured in the storm. | L7: Relevant | M7: C | N7: =IF(M7="","",IF(M7="A",1,IF(M7="B",0.5,IF(M7="C",0,IF(M7="D",-1,IF(M7="E",0,"")))))) -> 0 | S7: =IF(R7="","",IF(R7="A",1,IF(R7="B",0.5,IF(R7="C",0,IF(R7="D",-1,IF(R7="E",0,""))))))
A8: 42 | B8: 1 | C8: California Freeze (January 2007) | D8: Freeze | E8: 20070111 | F8: 20070117 | G8: CA | H8: https://www.washingtonpost.com/archive/business/2007/01/20/california-freeze-puts-squeeze-on-citrus-crop-span-classbankheadprices-to-rise-as-cold-curtails-orange-vegetable-harvests-span/edcfcc6e-357a-4233-904d-18badcaccac7/ | I8: California Freeze Puts Squeeze on Citrus Crop - The Washington Post | J8: Jan 20, 2007 ... California Freeze Puts Squeeze on Citrus Crop. Prices to Rise as Cold ... 2007More than 19 years ago. Make us preferred on Google. By Annys Shin. | K8: Take a big bite of that juicy navel orange. It may be the last one you enjoy for a while. More than a week of icy temperatures in California damaged an estimated $500 million or more of fruit and vegetable crops. With another dip in the mercury predicted for early next week, the worst freeze in California in eight years is not over. And consumers nationwide are likely to see its effects for weeks and even months on their grocery bills. "Consumers can expect to see higher prices on produce," Giant Food spokesman Barry F. Scher said. The only question is how much higher. Growers, retailers, economists and government officials say they will not know that until the cold spell ends and they can finish assessing the damage. "Everything is a guess at this point," said Claire Smith, a spokeswoman for Sunkist Growers, a cooperative of 6,000 California and Arizona citrus growers. Prices for navel oranges may begin rising as early as next week and might not go down until late spring, said Joel Nelsen, president of California Citrus Mutual, which represents 2,000 citrus growers. California growers do know they will be shipping fewer oranges, avocados, strawberries, artichokes, lettuce, broccoli, cabbage, cauliflower and celery. They expect, however, that the supply of strawberries could bounce back quickly. Plants that were not damaged by the cold temperatures should be able to produce more fruit in another four to six weeks, said Peggy Dillon of the California Strawberry Commission. Artichoke farmers are hopeful that freeze-damaged plants will yield another harvest in two months, said Doug Mosebar, president of the California Farm Bureau Federation. And lettuce is grown year-round in different parts of California and Arizona, so any interruption in production is likely to be temporary. Retailers may also be able to spare consumers large spikes in the prices of some commodities by turning to other domestic and foreign sources -- Mexico for avocados, Florida for Valencia oranges and grapefruit. "Giant, like every other retailer, will be looking for alternatives if we are unable to purchase from our regular vendors," Scher said. The disruption in the supply of California oranges, however, will be harder to contain, economists and industry leaders predicted. California is the nation's top producer of table citrus and about three-quarters of the annual crop was still on trees when the freeze set in during the wee hours of Jan. 12, turning the insides of much of the crop to mush. Because citrus trees produce fruit only once a year, the frigid conditions cut the harvest short. The peak market for Florida Valencia oranges begins in April. Navel oranges from Australia and South Africa don't start arriving until summer. As a result, California citrus growers are hoping for double the return on the fruit they manage to salvage, charging more and shipping some fruit with a less than perfect complexion. How much of that cost will be passed on to consumers isn't yet clear. Harris Teeter spokeswoman Jennifer Panetta said the supermarket chain's suppliers have already doubled prices for citrus fruits. But before passing those costs onto consumers, "we're going to see if we can get citrus from other parts of the world," she said. Sodexho, the food and facilities management giant based in Gaithersburg, may end up absorbing some of the increased costs for fruits and vegetables. Cafeteria prices at universities, for example, probably won't go up because of the freeze, said Dexter Tompkins, Sodexho's director of supply management for produce. "We still have to have a salad bar and offer lettuce and tomatoes on sandwiches," he said, adding, "Maybe we won't offer orange segments anymore" and instead offer pineapple or other alternatives. In fact, growers of other fruits may be in for a small windfall due to the coming orange shortage. H. Dave Carlson, president of the Washington state apple commission, said since the freeze, apple growers in his state have received more orders from distributors. He expects grocery store prices on Washington apples to inch up 10 to 15 cents a pound. But any upward pressure on prices for fruits and vegetables not directly affected by the freeze is likely to be limited, Wells Fargo economist Michael Swanson said. "These are very discrete seasonal markets," he said. Just as banana prices behave differently than orange prices, consumers should not expect to pay more for orange juice, which is made primarily with oranges from Florida, not California. The freeze has prompted speculators to drive up the price of frozen-concentrated orange-juice futures. But agricultural economists say investors need to bone up on their geography. "I would be more afraid of a freeze in Brazil," another major supplier of juicing oranges, Swanson said. "It's not a logical response." Speculators "are probably not jumping on the right horse here," University of Florida economist Tom Spreen said. If you can't bear to give up those juicy oranges just yet, you might want to start shopping now. Any fruit in stores up until now was picked before the freeze. On Wednesday, prices at local stores such as Whole Foods, Giant and Safeway reflected that, with a medium-sized navel orange costing an average of 50 cents. If you're shopping later in the week, when oranges that survived the freeze start arriving, Swanson says you might try being less picky. "The quality of the fruit is not affected, but the cosmetic appeal might be," he said. | L8: Relevant | M8: C | N8: =IF(M8="","",IF(M8="A",1,IF(M8="B",0.5,IF(M8="C",0,IF(M8="D",-1,IF(M8="E",0,"")))))) -> 0 | S8: =IF(R8="","",IF(R8="A",1,IF(R8="B",0.5,IF(R8="C",0,IF(R8="D",-1,IF(R8="E",0,""))))))
A9: 53 | B9: 8 | C9: Midwest Flooding (Summer 2008) | D9: Flooding | E9: 20080401 | F9: 20080630 | G9: IA,IL,IN,KS,MI,MN,MO,ND,NE,OH,SD,WI | H9: https://www.nytimes.com/2008/06/16/us/16midwest.html | I9: In Midwest Floods, a Broad Threat to Crops - The New York Times | J9: Jun 16, 2008 ... https://www.nytimes.com/2008/06/16/us/16midwest.html. Share full ... Midwest flooding may lie ahead. Credit...Stephen Mally for The New ... | N9: =IF(M9="","",IF(M9="A",1,IF(M9="B",0.5,IF(M9="C",0,IF(M9="D",-1,IF(M9="E",0,"")))))) | S9: =IF(R9="","",IF(R9="A",1,IF(R9="B",0.5,IF(R9="C",0,IF(R9="D",-1,IF(R9="E",0,""))))))
A10: 53 | B10: 10 | C10: Midwest Flooding (Summer 2008) | D10: Flooding | E10: 20080401 | F10: 20080630 | G10: IA,IL,IN,KS,MI,MN,MO,ND,NE,OH,SD,WI | H10: https://www.chron.com/news/nation-world/article/Floods-wreak-havoc-throughout-Midwest-1765722.php | I10: Floods wreak havoc throughout Midwest - Chron | J10: Jun 11, 2008 ... ➕ Make Chron your preferred Google source · News|U.S. & World. Floods wreak havoc throughout Midwest. By Associated Press June 11, 2008. | K10: DES MOINES, IOWA — Rising rivers wiped out an Iowa railroad bridge Tuesday, flooded Illinois farmland and forced residents along the Mississippi River to prepare for what could be the worst flooding in 15 years. In Cedar Falls, Iowa, officials were readying residents and downtown business owners to evacuate as the Cedar River threatened to spill over a levee. The river was expected to top the levee early today, prompting a mandatory evacuation of downtown, Mayor Jon Crews said. "I've been downtown for 37 years and I have never seen anything like this," said Steve Schomaker, a partner in a local insurance company. Levee breaks Tuesday in southeastern Illinois flooded 50 to 75 square miles of farmland along the Embarras River, forcing the evacuations homes northeast of Lawrenceville, said Lawrence County Sheriff Russell Adams. He said water was up to the roofs of some rural homes. In Elnora, Ind., about 100 miles southwest of Indianapolis, berms of white sandbags and concrete barriers held back the White River, leaving residents little choice but to wait and watch. Most residents left after voluntary evacuation orders came late Monday, two days after the area got up to 10 inches of rain. "We have a very touch-and-go situation there, but everything that can be done has been done," Indiana Gov. Mitch Daniels said. Along the Mississippi River, the National Weather Service on Tuesday predicted crests of 10 feet above flood stage and higher over the next two weeks. Most of the towns are protected by levees, but outlying areas could be flooded. | L10: Relevant | M10: C | N10: =IF(M10="","",IF(M10="A",1,IF(M10="B",0.5,IF(M10="C",0,IF(M10="D",-1,IF(M10="E",0,"")))))) -> 0 | S10: =IF(R10="","",IF(R10="A",1,IF(R10="B",0.5,IF(R10="C",0,IF(R10="D",-1,IF(R10="E",0,""))))))
A11: 55 | B11: 6 | C11: Hurricane Gustav (September 2008) | D11: Tropical Cyclone | E11: 20080831 | F11: 20080903 | G11: LA | H11: https://www.npr.org/2008/09/01/94174382/hurricane-gustav-makes-landfall | I11: Hurricane Gustav Makes Landfall - NPR | J11: Sep 1, 2008 ... NPR's Greg Allen offers an on-the-ground report from Louisiana. Hurricane Gustav Storms Past New Orleans ... Players of the United States pose for ... | K11: TONY COX, host: From NPR News, this is News & Notes. I'm Tony Cox. Hurricane Gustav has landed. The category two hurricane hit this morning just southwest of New Orleans in Cocodrie, Louisiana. Close to two million residents were evacuated from the Gulf Coast over the weekend. The storm has prompted Republicans to change their convention plans as the country keeps a close eye on the powerful storm. In a few moments we'll get an update from the Republican National Convention in Minnesota from NPR's senior Washington editor Ron Elving. But right now, we have NPR's Greg Allen who is here to give us an on-the-ground report from Louisiana. Greg, Welcome. GREG ALLEN: Hi, Tony. COX: How bad were things when the storm actually hit? ALLEN: Well, we all expected a very powerful storm yesterday. We thought it could be as much as a category four when it made landfall here. So, you know, New Orleans prepared for a storm that was at least as bad as Katrina. That's what we were looking at. When the storm came ashore, when Gustav made land, he made landfall about, well, many miles southwest of New Orleans and actually, as you say, came - made landfall as a much less intense hurricane, category two. What that means for New Orleans being farther away and being less intense, the wind speeds we've seen here were not what we expected or what we prepared for. It's hard to say - we'll get a final read from the meteorologists and the assessors later about how - what the wind speeds were here, but suffice to say that the storm we saw come through New Orleans today was less than what we expected. COX: In another way, Greg, the storm was very different from Katrina as far as the evacuation of residents. As we understand it, close to two million people were evacuated over the weekend. That must have made things quite different this time. ALLEN: Exactly, Tony. The catch word around town is lessons learned. You hear that over and over again from public officials, but I've heard a lot from residents. People who were leaving town when I was talking to them at the bus and train station when they were preparing to board buses and trains out of town over the weekend. People were saying, I stayed during Katrina, I didn't like what happened here. It was not a pleasant place to be and so I'm taking advantage of the government's help here. And you have to say that the city of New Orleans and the state of Louisiana did an exceptional job evacuating people out of this city. They moved tens of thousands of people out of here through buses and trains. As I say, picking them up in city neighborhoods, bringing them to a central location, getting them out of town and then getting them settled in shelters up in northern Louisiana and also in other states nearby. So it's an effort that cost a lot of money and took a lot of planning, but we have to say, went off very well. COX: At the same time, though, Greg, a number of people stayed, actually. Some who stayed through Katrina. Did you talk to any of them, and can you give us a sense of why people felt they should stay again - certainly given their experiences with Katrina three years ago? ALLEN: It's interesting, Tony. I just spent some time out driving around talking to people we found out sitting out on their porches. I was out there with reporter John Burnett (ph), and we talked to many people. I got to say that everybody we talked to had a gun. And that's New Orleans in a hurricane. People are there to protect their property. That's one reason some people stayed. Another reason is some people said - one lady said, I just wasn't prepared to go some place. I didn't want to go spend money I don't want to spend, to be some place I don't want to be. So she said we just decided we're going to stay. It was as simple as that. Some of these people I spoke to, in fact, all of them were very well prepared. They had generators, they have hardened houses with a - some of them had boards up. But at the same time, they're doing -the one family we visited with, they were having a traditional New Orleans hurricane celebration. They were drinking a bottle of '89 champagne out on their porch preparing to make - use filet mignon for steak and eggs. So that's the uptown section of New Orleans. We haven't got to the other part of town where people are maybe not sitting out the storm in such high style. But there are people who believe that the best place to be when a storm hits is at your home. COX: Now the Ninth Ward certainly was one of the hardest hit areas from Katrina. Have you heard anything at all about what took place down there? ALLEN: The one concern we've been dealing with today is there's a little bit of flooding in the Ninth Ward. And flooding might be putting it strongly, but what we're seeing - what we've been seeing today is some water lapping over the top of the restored levee there. The Army Corps of Engineers, at this point, has been reassuring us that it's just water splashing over the top. However, that said, there's a substantial amount of water that has splashed over the top. They say that there's still plenty of clearance and that they don't expect widespread flooding there. But they have - one difference between now and Katrina is that they have crews on site to monitor it and to take steps immediately if there's any threat of flooding. COX: Greg, thank you very much. ALLEN: You're welcome, Tony. COX: That was NPR's Greg Allen in New Orleans. | L11: Relevant | M11: C | N11: =IF(M11="","",IF(M11="A",1,IF(M11="B",0.5,IF(M11="C",0,IF(M11="D",-1,IF(M11="E",0,"")))))) -> 0 | S11: =IF(R11="","",IF(R11="A",1,IF(R11="B",0.5,IF(R11="C",0,IF(R11="D",-1,IF(R11="E",0,""))))))
A12: 100 | B12: 13 | C12: Hurricane Isaac (August 2012) | D12: Tropical Cyclone | E12: 20120826 | F12: 20120831 | G12: LA,MS | H12: https://www.npr.org/sections/thetwo-way/2012/08/28/160157839/isaac-on-the-verge-of-hurricane-strength-forecast-for-landfall-tonight | I12: Hurricane Isaac Makes Landfall In Southeast Louisiana, Headed For ... | J12: America. Hurricane Isaac Makes Landfall In Southeast Louisiana, Headed For Baton Rouge. August 28, 20125:15 PM ET. By. Krishnadev Calamur. ,. | K12: The Latest At 11:06 P.M. ET Little Change In Strength The National Hurricane Center says Hurricane Isaac will continue moving near or over the southeastern coast of Louisiana on Tuesday night, and move inland during the next day or so. "Little change in strength is forecast tonight," it said at 10 p.m. CDT. "Slow weakening is expected after that." As we reported earlier, widespread flooding was expected. Isaac was moving toward Baton Rouge, La. Our original post and earlier updates continue: Seven years ago tomorrow, Hurricane Katrina ravaged New Orleans. Today, the area is facing its first big test in the form of Hurricane Isaac. While the storms are not comparable — Katrina was a monster category 3 storm, whil Isaac is forecast to make landfall as a weak hurricane — the cyclone has triggered evacuations and an emergency declaration in Louisiana. The latest advisory from the National Hurricane Center still says that the central pressure of the storm has dropped and the winds around the center are picking up steam. The latest forecast has the Isaac making landfall along the Mississippi or Southeast Louisiana coast as a hurricane with 80 mph winds. We'll update this post throughout the day. So hit your refresh button to see the latest. The Latest At 10 P.M. ET Isaac Headed For Baton Rouge It appears Isaac is headed straight for Baton Rouge, La. Ed Rappaport, deputy director of the National Hurricane Center, told The Associated Press the hurricane's core would pass west of New Orleans and head for Baton Rouge. He said the storm would then weaken. The Latest At 9:20 P.M. ET: In its latest update, the National Hurricane Center says Isaac is moving northwest at around 8 mph. It adds: "A NORTHWESTWARD MOTION AT A SLIGHTLY SLOWER SPEED IS EXPECTED OVER THE NEXT DAY OR TWO. ON THE FORECAST TRACK...THE CENTER OF HURRICANE ISAAC WILL CONTINUE MOVING NEAR OR OVER THE SOUTHEASTERN COAST OF LOUISIANA OVER THE NEXT FEW HOURS...AND MOVE FARTHER INLAND OVER SOUTHEASTERN LOUISIANA DURING THE NEXT DAY OR SO." The Category 1 Hurricane has maximum sustained winds nears 80 mph. The center warns of flooding in Mississippi and southeastern Louisiana, Alabama, south-central Louisiana, the Florida panhandle, Apalachee Bay and the remainder of Florida west coast. In Biloxi, Miss., Shirley Eleutrius, who lives just two blocks from the Mississippi Sound, which is flooding the highway, tells NPR's Debbie Elliott that for now, she's staying put. "We've lived through all kinds of storms," she says. "Just ride it out. Be honest with you nothing you can do but leave, you got to higher ground and that's wehre you stay." Updates on the storm's impact on New Orleans can be found on the website of our member station WWNO. The Latest At 8:10 P.M. ET: The National Hurricane Center says the storm's center reached land at 6:45 p.m. (local time) in Plaquemines Parish, about 90 miles southeast of New Orleans with winds near 80 mph. The storm's impact is expected to be felt in New Orleans and beyond. Here's more from the center's website: "ISAAC MAKES LANDFALL IN EXTREME SOUTHEASTERN LOUISIANA... ...STRONG WINDS AND A DANGEROUS STORM SURGE OCCURRING ALONG THE NORTHERN GULF COAST... ...U.S. Warnings in Effect..." The Latest at 7:06 p.m. ET: The center of Hurricane Issac should reach the southeastern Louisiana coast in the next few hours, the National Hurricane Center's latest update says. Issac is moving northwest at 8 mph, the center said, adding that it would continue moving over the southeastern part of the state during the next day or so. Here's more from the update: "MAXIMUM SUSTAINED WINDS ARE NEAR 80 MPH...130 KM/H...WITH HIGHER GUSTS. ISAAC IS A CATEGORY ONE HURRICANE ON THE SAFFIR-SIMPSON HURRICANE WIND SCALE. SOME SLIGHT STRENGTHENING IS POSSIBLE BEFORE ISAAC MAKES LANDFALL. GRADUAL WEAKENING IS EXPECTED AFTER LANDFALL OCCURS." NPR's Debbie Elliott is reporting on the storm for our Newscast Unit. Here's what Craig Fugate, head of the Federal Emergency Management Agency, told her: "This isn't just going to be a coastal storm, and the category of the storm doesn't always tell you what the impacts are going to be," he said. "Heavy rain and tropical force winds over large areas can be very disruptive, power outages, a lot of flooding. And we can't really forecast where that's going to happen, so we just need people to be aware of it and be ready." The Latest at 5:10 p.m. ET: -- The center of Hurricane Isaac is moving toward its expected landfall tonight at a rate of 8 miles per hour, and it is likely to strike the southeastern Louisiana coast as a category 1 hurricane, according to the National Hurricane Center's latest update. The service says the storm is "getting better organized" as it nears the coast, with maximum winds measured at 80 mph. Currently moving northwest toward land, Isaac is about 30 miles from the mouth of the Mississippi River. The storm is projecting hurricane-strength winds (75 mph and up) for a distance of 60 miles from its center, with the most powerful winds concentrated in the northeast and east, according to the hurricane center. Projections show the storm heading toward a spot just south of the mouth of the Mississippi. -- In a televised speech from the White House's Diplomatic Room, President Obama urged residents to heed warnings from local officials. "We're dealing with a big storm and there could be significant flooding and other damage across a large area," he said. "Now is not the time to tempt fate. Now is not the time to dismiss official warnings. You need to take this seriously." -- Louisiana Gov. Bobby Jindal said that 41 parishes have declared states of emergency and 7 parishes have issued mandatory evacuation orders. -- President Obama issued an emergency declaration for some areas of Mississippi. The Latest at 3:45 p.m. ET: -- Isaac is now a category 1 hurricane. The National Hurricane Center reported on its Twitter feed that reconnaissance data gathered by hurricane hunters found maximum winds of 75 mph. In its latest advisory, the National Hurricane Center said dry air pumping into the cyclone has kept it from intensifying further, and they are expecting it to make landfall with 80 mph winds. At this point, the Southeast Louisiana coast seems to be where the storm will make landfall. Update at 3:56 p.m. ET. The Scene In Gulfport: NPR's Russell Lewis sent this report from Gulfport, Miss.: "It's cloudy and windy. The rains are starting and stopping here. Gas stations are beginning to run out of certain grades of fuel. "There are dozens of power trucks lined up in a Walmart parking lot getting ready to roll to deal with possible power outages. "Hotels here are very tight. There are no vacancies and it will be difficult for people to find rooms if they choose to evacuate." Update at 3:349 p.m. ET. Rain, Wind Begin Miss., La.: The first rain bands from Isaac have started making their way through Miss. and La. A quick glance at a Weather Underground radar map tells us that rain is extending from New Orleans to Pascagoula. Some weather stations are reporting winds a little bit stronger than 40 mph. Online, videos of the Gulf starting to make its way onto coastal roads is popping up. Here's one from Waveland, Miss. Update at 1:22 p.m. ET. Not 'A Katrina-Type Event': Mitch Landrieu, the mayor of New Orleans, said the area dodged bullet today. The city, he said, could have been facing a category 3 hurricane. Still, he said, Isaac is "plenty big enough to cause a lot of hurt." "We are not expecting a Katrina type event," Landrieu said. "That is not to say that we will not see flooding." Update at 12:44 p.m. ET. A Slow Moving Storm: During a televised press conference, Louisiana Gov. Bobby Jindal said this is a slow moving storm and some areas of his state could face sustained tropical storm force winds for 24 to 36 hours. Jindal said the problem with this storm, however, will likely be flooding: As it lumbers through the area it will dump incredible amounts of rain that "will result in localized flooding." Already, Jindal said, 41 parishes have declared states of emergency and 7 parishes have issued mandatory evacuation orders. But the state government is prepared. They have aircrafts and boats standing by to lead rescue efforts if needed, Jindal said. Update at 12:29 p.m. ET. Now A Hurricane: The National Hurricane Center tweets: "Hurricane #Isaac update issued. Reconnaissance data indicate #Isaac finally achieves hurricane status." Update at 11:00 a.m. ET. Still A Tropical Storm: In its 11 a.m. advisory, the Hurricane Center has some good news: Top winds for Isaac remain at 70 mph. The center has also lowered its intensity forecast, now saying it will make landfall with top winds of 80 mph, making Isaac a minimal category 1 hurricane. The center reports: "Isaac is a large tropical cyclone. A dangerous storm surge, heavy rainfall and strong winds extend well away from the center and are expected to affect a large portion of the northern gulf coast. "For this reason, it is important not to focus on the exact center location. The threat of heavy rainfall and flooding is also expected to spread inland over the lower mississippi valley region during the next few days." Update at 10:12 a.m. ET. Now Not The Time 'To Tempt Fate': In a short statement from the White House, President Obama said that federal officials have been on the ground in places impacted and about to be affected by Tropical Storm Isaac for more than week. Obama said the federal government is ready to respond and that he has signed an emergency declaration for Louisiana so it could quickly get the help it needs. Obama added that people in the path of the storm should heed warnings from their local officials. "Now is not the time to tempt fate," Obama said. "You need to take this seriously." Update at 7:46 a.m. ET. Storm Surge Threat: As The New York Times reports, the danger of this storm may not be the winds but the storm surge, or the wall of water the storm is pushing toward land as it rumbles across the Gulf of Mexico. The Times adds: "Officials encouraged those in low-lying areas to leave, warning of 12-foot storm surges along a broad swath of the coast and days of nonstop rainfall, in some places possibly adding up to 20 inches of water. "'A slow-moving, large system poses a lot of problems,' Rick Knapp, the director of the National Hurricane Center, said in a conference call with reporters, describing the risks as 'life-threatening, potentially.'" Update at 7:45 a.m. ET. New Orleans Is Prepared: The storm is of course causing great concern because it was seven years ago tomorrow that Hurricane Katrina tore through New Orleans. As we reported, this is not the monster storm Katrina was and the levees and flood walls were rebuilt after Katrina. The New Orleans Times Picayune reports today that local officials are expressing nothing but confidence in the $15 billion system built to withstand a category 3 hurricane. | L12: Relevant | M12: C | N12: =IF(M12="","",IF(M12="A",1,IF(M12="B",0.5,IF(M12="C",0,IF(M12="D",-1,IF(M12="E",0,"")))))) -> 0 | S12: =IF(R12="","",IF(R12="A",1,IF(R12="B",0.5,IF(R12="C",0,IF(R12="D",-1,IF(R12="E",0,""))))))
A13: 113 | B13: 1 | C13: Western/Plains Drought/Heat Wave (Spring-Fall 2013) | D13: Drought | E13: 20130301 | F13: 20131130 | G13: AK,AZ,CA,CO,HI,ID,KS,MT,ND,NE,NM,NV,OK,OR,SD,TX,UT,WA,WY | H13: https://stateimpact.npr.org/oklahoma/2013/07/18/tree-program-to-combat-dust-is-dying-after-years-of-drought-and-disrepair/ | I13: In Western Oklahoma, Drought Threatens Trees Planted to Prevent ... | J13: Jul 18, 2013 ... ... of the windbreaks are dying from drought and lack of maintenance. The dirty 1930s left a permanent mark on the Great Plains. To help prevent ... | K13: The dirty 1930s left a permanent mark on the Great Plains. To help prevent another Dust Bowl, federal foresters planted more than a hundred million trees and built a giant windbreak that stretched from Texas to Canada. This massive planting effort was born in western Oklahoma, but many of the trees that helped save the state from its own harsh environment are dying off. | L13: Relevant | M13: C | N13: =IF(M13="","",IF(M13="A",1,IF(M13="B",0.5,IF(M13="C",0,IF(M13="D",-1,IF(M13="E",0,"")))))) -> 0 | S13: =IF(R13="","",IF(R13="A",1,IF(R13="B",0.5,IF(R13="C",0,IF(R13="D",-1,IF(R13="E",0,""))))))
A14: 132 | B14: 3 | C14: Western and Alaskan Wildfires (Summer-Fall 2015) | D14: Wildfire | E14: 20150601 | F14: 20151130 | G14: AK,AZ,CA,CO,HI,ID,MT,NM,NV,OR,UT,WA,WY | H14: https://www.marinij.com/business/20150823/western-wildfires-firefighters-to-get-additional-resources/ | I14: Western wildfires: Firefighters to get additional resources – Marin ... | J14: Aug 23, 2015 ... The U.S. Forest Service says the fire near Snow Summit Ski Resort south of Big Bear Lake has forced evacuation orders for about 400 homes, many ... | K14: Firefighters across the West saw little relief over the weekend as wildfires raged in the drought-stricken region, but for those in Washington, other states will soon provide additional resources. A look at large Western wildfires: ___ WASHINGTON Fire officials say a complex of wildfires burning in north-central Washington has grown to cover 374 square miles. Infrared mapping found the fires spread about 19 square miles Saturday evening. Fire spokeswoman Suzanne Flory says there could be some explosive fire growth Sunday if a cap of smoke lifts from Okanogan County, as has been forecast. When the smoke lifts on a wildfire, humidity drops, heat rises and fires can flare up. Flory says it’s similar to what happens when the flue is opened on a fireplace. Flory says the good news is that less smokes means restrictions on air travel will be lifted and more fire tankers can fly over and drop water and chemical retardant. Meanwhile, officials have downgraded some evacuation notices, allowing some people to return to their homes. On Sunday evening, the state Department of Health said that should nearby wildfires reach the site of a now-defunct uranium mine in Stevens County in eastern Washington, the smoke won’t be any more toxic than the standard smoke from a wildfire. In an announcement, the department said that radioactive materials at the Midnight Mine, which is about three miles northwest of Wellpinit on the Spokane Reservation, “won’t exacerbate the dangers of wildfire smoke if the fires overtake the site as the naturally occurring radioactive material stays in its original rock form and does not burn.” ___ CALIFORNIA Planes and helicopters were making major liquid drops on a wildfire that broke out Sunday afternoon near a ski resort in the San Bernardino Mountains, bringing the first gains against the blaze. The U.S. Forest Service says the fire near Snow Summit Ski Resort south of Big Bear Lake has forced evacuation orders for about 400 homes, many of them cabins and vacation houses. It has grown to 85 acres, but it is 10 percent contained. Water cannons from the ski resort usually used for making snow are being pointed toward the fire. Earlier Sunday, firefighters were gaining ground against a wildfire that led to the evacuation of thousands of people and destroyed a lodge in Kings Canyon National Park. Despite relentlessly high temperatures, fire crews increased the blaze’s containment to 7 percent, the U.S. Forest Service said. The wildfire has burned across more than 73 square miles of timber and brush left parched by the state’s extended drought. At least 2,500 campers, hikers, employees and residents fled the area last week, including staffers and summer campers at The Hume Lake Christian Camp. Nobody was hurt when the Kings Canyon lodge, which bills itself as a folksy getaway for tourists, was burned to its foundation. The lightning-sparked blaze has been burning for three weeks. It is one of 15 wildfires burning across California. ___ MONTANA Firefighters and residents are bracing for a return to more intense fire activity in western Montana where wildfires have scored thousands of acres and threatened some small communities. A fire weather watch posted Sunday warned that gusty winds and low humidity were expected Monday afternoon in Glacier National Park and the Kootenai and Flathead national forest areas. On Glacier’s southern boundary, a wildfire is about a mile south of the town of Essex where about 100 area residents have been advised to be ready to evacuate. Fire spokesman Jonathan Moor says crews are working to keep the fire away from the town but it’s difficult to predict what the fire will do over the next couple of days. ___ OREGON Cooler temperatures and reduced winds helped firefighters on Saturday who were battling a large wildfire in Oregon south of the towns of John Day and Canyon City. Fire officials expect wind to pick up on Sunday, but since winds were expected to blow out of the southeast, they will send the fire back into an area that has already burned. The lightning-caused Canyon-Creek Complex of fires has burned about 109 square miles since Aug. 12. To the northeast, firefighters also made progress Saturday on the Grizzly Bear Complex of fires in northeast Oregon and southeast Washington. The five-lightning caused fires have burned more than 95 square miles since Aug. 13. | L14: Relevant | M14: C | N14: =IF(M14="","",IF(M14="A",1,IF(M14="B",0.5,IF(M14="C",0,IF(M14="D",-1,IF(M14="E",0,"")))))) -> 0 | S14: =IF(R14="","",IF(R14="A",1,IF(R14="B",0.5,IF(R14="C",0,IF(R14="D",-1,IF(R14="E",0,""))))))
A15: 132 | B15: 12 | C15: Western and Alaskan Wildfires (Summer-Fall 2015) | D15: Wildfire | E15: 20150601 | F15: 20151130 | G15: AK,AZ,CA,CO,HI,ID,MT,NM,NV,OR,UT,WA,WY | H15: https://www.marinij.com/general-news/20150618/western-wildfires-blazes-burn-in-4-states-amid-hot-weather/ | I15: Western wildfires: Blazes burn in 4 states amid hot weather – Marin ... | J15: Jun 18, 2015 ... A smoky brush fire near a rural Arizona community was contained mainly to a dry riverbed, allowing most of the hundreds of evacuated residents ... | K15: Wildfires are chewing through parched parts of the West, where temperatures are rising Thursday. Here’s a look at the latest hotspots and what crews are doing to control them. ___ ALASKA Two wildfires are burning outside Anchorage, one that tripled in size and forced the evacuation of campsites on the Kenai Peninsula and another in the heart of Alaska’s dog-mushing community that firefighters have kept from growing. A blaze in the Kenai National Wildlife Refuge ballooned to about 14 square miles as temperatures warmed in low humidity. Eight structures — anything from a home to a chicken coop — have been destroyed since Monday. More than 250 firefighters battled the blaze between a highway and the Kenai River, Alaska’s most popular sport-fishing venue. Up to 500 more personnel are expected from the Lower 48 states. More than 420 firefighters have kept another wildfire at about 12 square miles, this one in Willow, where the Iditarod Trail Sled Dog Race normally begins. Some residents were expected to return Thursday to the community about 40 miles north of Anchorage. A preliminary assessment showed 132 properties were in the burned area and 26 homes were destroyed, the Matanuska-Susitna Borough’s Facebook page said Thursday. ___ ARIZONA A smoky brush fire near a rural Arizona community was contained mainly to a dry riverbed, allowing most of the hundreds of evacuated residents to return home. The flames have burned at least three residences near Kearny, about 85 miles southeast of Phoenix, and torn through nearly 2 square miles of salt cedar trees since Wednesday. A handful of people who live close to a riverbed must stay away because of their homes’ proximity to the fire, Arizona State Forestry spokesman Mike Reichling said. Some firefighters who faced triple-digit temperatures suffered heat-related problems, but there were no serious injuries, he said. About 200 firefighters have kept it burning away from the town of 2,000 residents, officials said. ___ CALIFORNIA A Southern California desert wildfire burned three homes Thursday and another blaze in the San Bernardino Mountains grew to over 15 square miles as smaller blazes erupted in drought-parched areas up and down the state. Small but fierce fires burned in grass, trees and brush. A 60-acre fire erupted in a palm grove in the desert town of Thermal, 135 miles southeast of Los Angeles. By late afternoon, it had burned three homes and several outbuildings, state fire officials reported. About an hour’s drive northwest, a wildfire burning since Wednesday exploded in size in a remote area of the San Bernardino National Forest. About 400 people, including residents of about two dozen homes and several hundred campers, many of them children, had been evacuated as the fire burned south of Big Bear Lake. Other fires being fought included a 100-acre blaze in Yuba County in the Sierra Nevada foothills north of Sacramento. More than a dozen homes were ordered evacuated after a training fire for state crews reportedly was swept out of control by gusty winds north of Smartsville. Crews also fought a 35-acre wildfire in Mariposa County; a 50-acre blaze in San Joaquin County; and a 40-acre fire near the Central California rural town of Bootjack that briefly forced evacuations. ___ WASHINGTON A wildfire burning south of Spokane was under control but sent up a massive smoke column in eastern Washington. Brian Schaeffer with the Spokane Fire Department says that air and ground crews got the less than 150-acre blaze halfway contained, Spokane news station KHQ-TV reported Thursday (http://bit.ly/1JXNFFm ). | L15: Relevant | M15: C | N15: =IF(M15="","",IF(M15="A",1,IF(M15="B",0.5,IF(M15="C",0,IF(M15="D",-1,IF(M15="E",0,"")))))) -> 0 | S15: =IF(R15="","",IF(R15="A",1,IF(R15="B",0.5,IF(R15="C",0,IF(R15="D",-1,IF(R15="E",0,""))))))
A16: 137 | B16: 1 | C16: Southern Severe Weather (March 2016) | D16: Severe Storm | E16: 20160317 | F16: 20160318 | G16: AL,AR,FL,GA,KY,LA,MS,NC,OK,SC,TN,TX,VA | H16: https://www.usatoday.com/story/weather/2016/03/22/weather-forecast-wednesday/82137006/ | I16: Wednesday's forecast: Snow north-central, stormy South - USA Today | J16: Mar 22, 2016 ... South: Severe storms are forecast to lash portions of the southern Plains and Mississippi Valley on Wednesday. ... hail and a few tornadoes. East: ... | K16: A big storm will bring blizzard conditions to the northern Plains and Upper Midwest Wednesday while severe storms and tornadoes hit the sodden South. Northern Plains, Upper Midwest: Heavy, wet snow is forecast to paste several states on Wednesday, all the way from Colorado to Michigan. Some of the heaviest snow is expected in Minnesota, Wisconsin and Michigan. South: Severe storms are forecast to lash portions of the southern Plains and Mississippi Valley on Wednesday. Northeastern Texas, eastern Oklahoma and much of Arkansas could see high winds, large hail and a few tornadoes. East: New England and parts of the Northeast will see chilly temperatures and some rain and show on Wednesday. The rest of the East Coast, from the Mid-Atlantic to Florida, will see clear skies and mild to warm temperatures. West: Light rain and snow is likely in the Northwest and northern Rockies. The rest of the West will be sunny and dry. Weather history for March 23: In 1913 (Easter Sunday), a ferocious tornado hit Omaha, Neb., killing 94 people. In 1995, Atlanta soared to 89 degrees, the city's warmest temperature ever recorded in March. | L16: Trash | N16: =IF(M16="","",IF(M16="A",1,IF(M16="B",0.5,IF(M16="C",0,IF(M16="D",-1,IF(M16="E",0,"")))))) | S16: =IF(R16="","",IF(R16="A",1,IF(R16="B",0.5,IF(R16="C",0,IF(R16="D",-1,IF(R16="E",0,""))))))
A17: 146 | B17: 23 | C17: Louisiana Flooding (August 2016) | D17: Flooding | E17: 20160812 | F17: 20160815 | G17: LA | H17: https://www.npr.org/sections/thetwo-way/2016/08/22/490916070/flooding-in-louisiana-raises-questions-about-timing-urgency-of-warnings | I17: Flooding In Louisiana Raises Questions About Timing, Urgency Of ... | J17: Aug 22, 2016 ... — NWS New Orleans (@NWSNewOrleans) August 8, 2016 ... in the Baton Rouge area began warning residents of potentially serious flooding on Aug. | K17: The rain fell for days, sometimes 3 inches or more in a single hour, as streets became rivers and rivers ate up entire neighborhoods in southeast Louisiana. Between Aug. 11 and Aug. 14, more than 20 inches of rain fell in and around East Baton Rouge, one of the hardest-hit parishes. And in some parishes in the region, as much as 2 feet of rain fell in 48 hours. The National Weather Service says the likelihood that so much rain would fall in so little time was about one-tenth of 1 percent. A flood this bad should only happen once every thousand years. As The Two-Way has reported, at least 13 people have died in the floods and some 60,000 homes were damaged. The Red Cross says it is likely the worst natural disaster since Superstorm Sandy in 2012 and that the response will cost at least $30 million. As the water recedes, many local leaders, weather forecasters and Louisiana residents are wondering whether people could have been better warned. Tracking the storm How a storm develops dictates who is responsible for warning people about it. This storm began as an area of low pressure over the Gulf of Mexico, where hurricanes are born, so from the beginning, the National Hurricane Center in Miami was monitoring it. "Our job at the National Hurricane Center is to forecast the strength and size of tropical cyclones," explains James Franklin, the chief of forecast operations at the National Hurricane Center, who has worked on hurricane forecasting since the 1980s. He used to fly into storms as part of the agency's airborne reconnaissance team. These days, he tries to steer clear of tropical storms and help others do the same. But this Gulf storm never became a hurricane. The wind speeds were very low. The middle of the system wasn't warmer than the edges, and air wasn't circulating around the center of the system the way it would in a cyclone. So the National Hurricane Center did not issue an advisory. This video shows NASA rainfall data from Aug. 8 to Aug. 15. More than 20 inches of rain fell in the areas depicted in pink on the map. "If a disturbance or weather event is not a depression zone or a hurricane, we don't write advisories on it," Franklin says. "It's not our authority to write advisories on things that are not hazardous cyclones." And he points out, "The best place to get local information is always the local office, even when the National Hurricane Center has written an advisory. The local office has the best information about local flood risk." In this case, the local New Orleans/Baton Rouge National Weather Service Weather Forecast Office says it recognized the potential for flooding as early as Aug. 8. On that day — nearly three days before the storm arrived — it began issuing advisories and warnings about heavy rain. One rainfall map warned of "isolated flash flooding" later in the week. Between Tuesday and Friday, when the first flash-flood emergencies were issued, the local weather service office for Baton Rouge says it issued at least a dozen advisories and warnings about flooding in southeastern Louisiana. Kenneth Graham, the meteorologist in charge at the local office of the National Weather Service, says the situation was particularly difficult for forecasters trying to provide block-by-block clarity to residents. "We broke all records," he writes in an email to NPR. "For the River Flood Warnings, there is no way to reference any previous flood event since there is no history to draw from." In the town of Denham Springs, the Amite River crested 4.5 feet above the previous record, and Graham explains that because the terrain is so featureless around Baton Rouge, "the water spreads out very far from the river," affecting an enormous area and tens of thousands of people. By Aug. 11, Graham's office had decided to do something it rarely does — elevate the flash-flood warnings for areas around Baton Rouge to flash-flood emergencies, which can be issued only when there is significant and immediate threat to life and property. Still, some residents say they were not adequately warned of the severity of the storm. Baton Rouge resident Linda Smith tells Ryan Kailath of member station WWNO that she would have heeded more-urgent notifications. She and her family barely escaped their home before it flooded. "We got no calls, no texts, no nothing," Smith says. "So that's why I didn't panic because I didn't hear a siren. I didn't hear anything." “It's important not to focus on the name or classification [of a storm], and instead focus on the hazards. Not everything that can be deadly or catastrophic is a tropical cyclone.” – James Franklin, chief of forecast operations at the National Hurricane Center More than a dozen people died and no one was evacuated from the area before the most serious rainfall began. The storm with no name Tropical storms and hurricanes are assigned names by the National Hurricane Center, which draws attention to the storms. "There certainly is more visibility that comes from cyclone," says Franklin of the National Hurricane Center. One reason for that, he says, is that the name and category designations — such as Hurricane Katrina, Category 5 — are more likely to be picked up by the media. Louisiana Gov. John Bel Edwards told the New Orleans Times-Picayune, "When you have a storm that is unnamed — it wasn't a hurricane, it wasn't a tropical event — people underestimate the impact that it would have." "It's important not to focus on the name or classification [of a storm], and instead focus on the hazards," Franklin says. "Not everything that can be deadly or catastrophic is a tropical cyclone." Franklin acknowledges that the National Weather Service shares responsibility for communicating storm hazards to the media. "There are often a lot of mixed signals out there, because the media is really focused on what [the National Hurricane Center] is saying about a storm, instead of the local office," he says. The metrics that forecasters use to describe storms can also be confusing if people don't understand the on-the-ground effects of a storm in their neighborhood. Franklin says his agency is rolling out a new storm-surge-warning system next year to highlight that hazard more clearly. But when it comes to communicating about flooding, he thinks the information forecasters provide is already pretty clear. "We have some pretty good metrics for rainfall," he says. "It's called inches." Many local newspapers, television stations and radio broadcasters in the Baton Rouge area began warning residents of potentially serious flooding on Aug. 11, the day the local NWS issued emergency warnings. As for national media outlets, many were late to the scene and slow in their coverage. Craig Fugate, the administrator for the Federal Emergency Management Agency, told the Times-Picayune newspaper last Tuesday, "You have the Olympics. You got the election. If you look at the national news, you're probably on the third or fourth page. ... We think it is a national headline disaster." Reflecting on NPR's own coverage of the flooding, Vice President of News Michael Oreskes said it was both swift and thorough. Oreskes says: "As the water rose NPR turned to our member stations in Baton Rouge and New Orleans for immediate news coverage by Friday, Aug. 12. By that Sunday, NPR's Southern correspondent, Debbie Elliot, had arrived from her home in Alabama, navigating around floodwaters on remote parish roads to get into Amite and Baton Rouge." The New York Times published its first story by a staff reporter on the evening of Aug. 14. Last week, the public editor of The Times published an apology for the newspaper's lack of timely coverage. She wrote: "No doubt this is a busy news period, and the fact that it is August compounds the usual challenges of getting available staff to the site of the news. But a news organization like The Times — rich with resources and eager to proclaim its national prominence — surely can find a way to cover a storm that has ravaged such a wide stretch of the country's Gulf Coast." | L17: Relevant | M17: C | N17: =IF(M17="","",IF(M17="A",1,IF(M17="B",0.5,IF(M17="C",0,IF(M17="D",-1,IF(M17="E",0,"")))))) -> 0 | S17: =IF(R17="","",IF(R17="A",1,IF(R17="B",0.5,IF(R17="C",0,IF(R17="D",-1,IF(R17="E",0,""))))))
A18: 154 | B18: 1 | C18: Southeast Freeze (March 2017) | D18: Freeze | E18: 20170314 | F18: 20170316 | G18: AL,FL,GA,KY,MS,NC,SC,TN,VA,WV | H18: https://www.washingtonpost.com/news/capital-weather-gang/wp/2017/03/21/get-ready-for-higher-fruit-prices-the-freeze-devastated-some-crops-in-the-south/ | I18: Get ready for higher fruit prices — the freeze devastated some crops ... | J18: Mar 21, 2017 ... ... freeze based on the climatology.” In other words, it's normal to get freezing temperatures in the Southeast in mid-March, so maybe we should ... | K18: After one of the warmest winters in recent memory, plants sprang to life well before they should have blossomed. Even on Feb. 1, as Phil the groundhog was declaring six more weeks of winter, spring had already arrived -- as much as 20 days earlier than normal in the Southeast. Then last week, the jet stream took a dive and allowed freezing temperatures to reach the Deep South. It was a massacre for fruit crops. Of the fruits (and farmers) that were affected, peaches and blueberries were the hardest hit, the Associated Press reported Monday night. Agriculture officials estimate the loss could be a whopping $1 billion, and South Carolina and Georgia are bearing the brunt of that burden. Georgia may be the "peach state," but South Carolina is the second-largest peach grower behind California. The state's agriculture department estimates an 85 percent loss in peaches this year. Blueberries in Georgia were cut 80 percent by the freeze. "We saw blueberry fields that had the potential to be the biggest and best crop of Georgia's production history that you would now not be able to find enough blueberries that survived the cold to make one pie," Georgia Agriculture Commissioner Gary Black told the AP. Strawberries and apples were damaged, too, though not to the extent of the blueberries and peaches, which appear to be a disaster from reports. David Streit, a forecaster for Commodity Weather Group and the Capital Weather Gang, said the damage will "for sure" mean higher prices for peaches this summer. The destruction occurred Thursday night, when temperatures bottomed out in the 20s, breaking records: * Savannah, Ga., tied its record low of 26 degrees * Jacksonville set a record low, plunging to 28 * Florence, S.C., dropped to 20 degrees, shattering its previous record of 25 * Charleston dipped to a record low 24 degrees, four degrees below its previous record * Gainesville, Fla. fell to 25, obliterating the previous record of 32 | L18: Relevant | M18: C | N18: =IF(M18="","",IF(M18="A",1,IF(M18="B",0.5,IF(M18="C",0,IF(M18="D",-1,IF(M18="E",0,"")))))) -> 0 | S18: =IF(R18="","",IF(R18="A",1,IF(R18="B",0.5,IF(R18="C",0,IF(R18="D",-1,IF(R18="E",0,""))))))
A19: 170 | B19: 2 | C19: Northeast Winter Storm (March 2018) | D19: Winter Storm | E19: 20180301 | F19: 20180303 | G19: CT,MA,ME,NH,NJ,NY,PA,RI,VT | H19: https://www.goerie.com/picture-gallery/news/2018/03/08/another-winter-storm-hits-the/557438007/ | I19: Another winter storm hits the Northeast - Erie Times-News | J19: Mar 7, 2018 ... More snow, wind makes it way through an already battered northeastern portion of the United States ... Another winter storm hits the Northeast. | K19: Snow sticks to a pedestrian crossing sign at the Burlington Riverfront Promenade during a snowstorm in Burlington City on Wednesday, March 7, 2018. [CARL KOSOLA / STAFF PHOTOJOURNALIST] Pat Measey of Burlington City cleans snow off her car on High Street in Burlington City on Wednesday, March 7, 2018. [CARL KOSOLA / STAFF PHOTOJOURNALIST] John Moore clears snow from his car before driving to Perkins for breakfast from The Glen at Bucks apartments during the second nor'easter Wednesday, March 7, 2018 in Warminster. [BILL FRASER / STAFF PHOTOJOURNALIST] A car travels Wednesday morning on Pulaski Highway in Pine Island, NY. ELAINE A. RUXTON/TIMES HERALD-RECORD Along Route 541 heading into Westampton, on Wednesday, March 7, 2018, winter driving conditions alert signs were posted for motorists. [NANCY ROKOS / STAFF PHOTOJOURNALIST] Josh Heron clears the sidewalk in front of his neighbor's place with a snowblower in Perkasie during the second snow storm to hit the area in the past week. on Wednesday, March 7, 2018. [ART GENTILE / STAFF PHOTOJOURNALIST] A couple and their dog take a walk through Fonthill on Wednesday, March 7, 2018, during the snowstorm. [KIM WEIMER / STAFF PHOTOJOURNALIST] Lance Goins, employed with moorestown township Public Works Department, shovels the sidewalk around Town hall, on Wednesday, March 7, 2018, as heavier snow starts to fall. [NANCY ROKOS / STAFF PHOTOJOURNALIST] From left, Ashley Allen, Georgia Kelso, Jordyn Fuges and Molly Kelso build a snowman during the nor'easter Wednesday, March 7, 2018, in New Britain Borough. [KIM WEIMER / STAFF PHOTOJOURNALIST] Lisa Ferketich shovels the sidewalk in front of her place of business on Reliance Rd in Souderton during the second snow storm to hit the area in the past week. [ART GENTILE / STAFF PHOTOJOURNALIST] A customer hurries to her car after grocery shopping at Wegmans in Mount Laurel, on Wednesday, March 7, 2018, as the wintry mix was changing into snow. [NANCY ROKOS / STAFF PHOTOJOURNALIST] A postal worker delivers mail in the nearly deserted streets of Doylestown Borough on Wednesday, March 7, 2018, as businesses were shut down because of the storm. [KIM WEIMER / STAFF PHOTOJOURNALIST] Motorists drive down route 130 in Edgewater Park as snow begins to make road conditions slick on Wednesday, March 7, 2018. [CARL KOSOLA / STAFF PHOTOJOURNALIST] Bill Grill clears a sidewalk on Oakland Ave.in Doylestown Borough on Wednesday, March 7, 2018. [KIM WEIMER / STAFF PHOTOJOURNALIST] Paul Hudrick, of Mount Laurel, clears the snow off of his car after grocery shopping at Wegmans in Mount Laurel, on Wednesday, march 7, 2018. [NANCY ROKOS / STAFF PHOTOJOURNALIST] Emmaleen Maltese, 4, tries catching snowflakes in her mouth outside her Perkasie home during the second snow storm to hit the area in the past week. [ART GENTILE / STAFF PHOTOJOURNALIST] Pat Measey of Burlington City cleans snow off her car on High Street in Burlington City on Wednesday, March 7, 2018. [CARL KOSOLA / STAFF PHOTOJOURNALIST] A truck salts route 206 in Columbus to prepare for the snow storm on Wednesday, March 7, 2018. [CARL KOSOLA / STAFF PHOTOJOURNALIST] A couple takes a walk through the snowy streets of Doylestown Borough on Wednesday, March 7, 2018. [KIM WEIMER / STAFF PHOTOJOURNALIST] A tree trimming crew and a Northampton Township Public Works truck travel along Second Street Pike during the second nor'easter Wednesday, March 7, 2018 in Richboro. [BILL FRASER / STAFF PHOTOJOURNALIST] Kyle Oswald clears the snow from his vehicle in Telford during the second snow storm to hit the area in the past week. [ART GENTILE / STAFF PHOTOJOURNALIST] A pedestrian makes their way along Bustleton Pike during a second nor'easter Wednesday, March 7, 2018 in Lower Southampton. [BILL FRASER / STAFF PHOTOJOURNALIST] A vehicle navigates Keeley Ave. in New Britain Borough during the blinding nor'easter Wednesday, March 7, 2018. [KIM WEIMER / STAFF PHOTOJOURNALIST] A van drives slowly through snow in the parking lot of the WaWa in Edgewater Park during a snowstorm on Wednesday, March 7, 2018. [CARL KOSOLA / STAFF PHOTOJOURNALIST] Erin Kyler, of Moorestown, heads into Lavita???s Pizzeria in moorestown, to pick up dinner for her family as the heavy snow comes down, Wednesday, March 7, 2018. [NANCY ROKOS / STAFF PHOTOJOURNALIST] Cars drive into the opposing lane of traffic on County Line Road to avoid a section of bamboo weighed down by wet snow during the storm Wednesday, March 7, 2018 in Upper Southampton. [BILL FRASER / STAFF PHOTOJOURNALIST] A car drives through slushy conditions on High Street in Burlington City during a snowstorm on Wednesday, March 7, 2018. [CARL KOSOLA / STAFF PHOTOJOURNALIST] A car travels Wednesday morning on Pulaski Highway in Pine Island, NY. ELAINE A. RUXTON/TIMES HERALD-RECORD | L19: Trash | N19: =IF(M19="","",IF(M19="A",1,IF(M19="B",0.5,IF(M19="C",0,IF(M19="D",-1,IF(M19="E",0,"")))))) | S19: =IF(R19="","",IF(R19="A",1,IF(R19="B",0.5,IF(R19="C",0,IF(R19="D",-1,IF(R19="E",0,""))))))
A20: 181 | B20: 8 | C20: Hurricane Florence (September 2018) | D20: Tropical Cyclone | E20: 20180913 | F20: 20180916 | G20: NC,SC | H20: https://www.charlotteobserver.com/news/state/north-carolina/article218455040.html | I20: Hurricane Florence: Death toll North Carolina South Carolina | J20: Sep 15, 2018 ... ... storm,” Cooper said in a statement. “Hurricane Florence is going to continue its violent grind across our state for days. Be extremely ... | K20: There have been 11 deaths in North Carolina and six in South Carolina linked to Hurricane Florence. Wilmington Police reported on Twitter that a tree fell on a house on Mercer Avenue, killing a mother and baby around 9:30 a.m. Friday. The father was pulled from the home and transported to a local hospital with injuries, police said. Gov. Roy Cooper confirmed one of the deaths occurred in Lenoir County, when someone was plugging in a generator, according to a press release. TV station WNCN said the 78-year-old victim and was “trying to connect two extension cords outside in the rain.” The station reported the fourth death involved a 77-year-old Kinston man who family members said died at 8 a.m. Friday when he was “blown down by the wind” while tending dogs. “Our hearts go out to the families of those who died in this storm,” Cooper said in a statement. “Hurricane Florence is going to continue its violent grind across our state for days. Be extremely careful and stay alert.” Three people died in Duplin County “due to flash flooding and swift water on roadways,” the Duplin County Sherrif’s Office announced Saturday. An 81-year-old man in Wayne County who fell and struck his head while packing to evacuate Friday is being counted as a storm-related death by the Office of the Chief Medical Examiner in Raleigh, The Associated Press reported. A husband and wife who died in a house fire in Cumberland County on Friday are also being counted as linked to the storm, according to the Associated Press and The Fayetteville Observer. A 3-month-old baby was killed Sunday after a tree fell on a mobile home in Dallas, N.C., according to Gaston County Commissioner Tracy Philbeck. The boy was home with family when the tree fell, reported The Charlotte Observer. No one else was hurt. In South Carolina, a 61-year-old woman died when the vehicle she was driving hit a fallen tree on Highway 18 near Union, The Associated Press reported. The tree was about 6 feet above the road surface and the vehicle’s roof struck the tree, Capt. Kelley Hughes of the South Carolina Highway Patrol told The Associated Press. The Horry County Coroner’s Office confirmed that Debra Collins Rion, 61, and Mark Carter King, 63, died Friday night from carbon monoxide poisoning from a generator, the Myrtle Beach Sun News reported. Georgetown County Coroner Kenny Johnson on Sunday said 23-year-old Michael Dalton Prince drowned in floodwaters inside an overturned truck, according to The (Myrtle Beach) Sun News. The South Carolina Department of Public Safety reported a fatal collision in Kershaw County Sunday at 7 a.m. A pick-up truck was north of Columbia on I-20’s westbound lanes, near the 106 mile marker, when it ran off the road and hit an overpass support beam. The driver, identified as 42-year-old Jeffery B. Youngren of Elgin, died on scene, according to the Kershaw County Coroner. Although Coroner David A. West reported Youngren was not wearing a seat belt, he said “the weather played a big part in his death.” Just before 5 p.m., the SCDPS reported another fatality on the road. This occurred at 6 a.m. in Lexington County, when a pick-up truck drove into standing water on Pond Branch Road, near the Columbia-area suburb of Gilbert, they said. 30-year-old Rhonda Rebecca Hartley of Leesville was pronounced dead at the scene, according to Lexington County Coroner Margaret Fisher, who said Hartley was not wearing a seat belt when she struck a tree. A person died inside the West Brunswick High School shelter Thursday morning, but that death was “not related to the storm,” according to Amanda Hutcheson, a Brunswick County spokeswoman. “We are saddened by the sudden passing of one of our community, and our hearts go out to the family and friends who are now grieving during such an already stressful period,” Hutcheson said in a statement. “An investigation into the cause of death is underway, but it appears there is no reason for others at the shelter to worry. Staff and responders at the shelters are committed to providing a safe location to citizens during the storm.” Carteret County reported two deaths on Saturday, but in a later news release said sheriff’s deputies and Army National Guard soldiers responding to a home found Pauly Lewis and his wife, Alicia Lewis dead “in an apparent murder/suicide.” Also in North Carolina, the death of a Pender County woman who officials said had a heart attack was not considered to be caused by the storm, The AP reported. The woman’s death was originally counted as storm-related because fallen trees had reportedly blocked rescuers from reaching her home. The deaths came as the storm was turning through the southeast part of the state, dumping more than 20 inches of rain in some communities. Gusts of winds in the 50 to 100 mph hour range were also reported since Hurricane Florence came ashore at 7:15 a.m. Friday, and the National Hurricane Center predicted trees would be knocked down. The National Hurricane Center says the high winds — combined with rain-soaked soil — will cause many trees to fall in coming days, crashing into homes, streets and onto power lines. | L20: Relevant | M20: C | N20: =IF(M20="","",IF(M20="A",1,IF(M20="B",0.5,IF(M20="C",0,IF(M20="D",-1,IF(M20="E",0,"")))))) -> 0 | S20: =IF(R20="","",IF(R20="A",1,IF(R20="B",0.5,IF(R20="C",0,IF(R20="D",-1,IF(R20="E",0,""))))))
A21: 194 | B21: 12 | C21: Mississippi River, Midwest and Southern Flooding (July 2019) | D21: Flooding | E21: 20190315 | F21: 20190731 | G21: AL,AR,FL,GA,IA,IL,IN,KS,KY,LA,MI,MN,MO,MS,NC,ND,NE,OH,OK,SC,SD,TN,TX,VA,WI | H21: https://www.nytimes.com/2019/03/16/us/nebraska-flooding.html | I21: Record-High Floods in Nebraska Breach Levees and Isolate Towns | J21: Mar 16, 2019 ... March 16, 2019. Several areas in the Midwest experienced record flooding this past week, with high water on Saturday causing more levee ... | K21: Several areas in the Midwest experienced record flooding this past week, with high water on Saturday causing more levee breaches on the Missouri River, prompting widespread evacuations and isolating neighborhoods and towns. Record-high river levels were reported in at least 38 locations in the Midwest, particularly in Nebraska and Iowa, said Jonathan Erdman, a senior meteorologist with weather.com. Heavy flooding was also reported in Wisconsin, Minnesota and South Dakota, and the National Weather Service said it would continue past the weekend. At least one man was confirmed dead in Columbus, Neb. The Omaha World-Herald reported that the man had been trying to help someone stranded by floodwaters on Thursday when a bridge collapsed as he was crossing it. Officials in Fremont County, Iowa, confirmed another flood-related death on Saturday. The devastation was captured in dramatic photographs circulated on social media by those who surveyed the damage. Senator Ben Sasse and Gov. Pete Ricketts of Nebraska showed how floodwaters from the Niobrara River in the northern part of the state had ripped through a dam on Thursday, releasing a torrent of water and depositing huge chunks of ice onto fields and roadways. They shared photos of water rushing over riverbanks and encircling homes and neighborhoods. Floodwaters had surrounded the town of Fremont, Neb., about 40 miles northwest of Omaha, said Councilwoman Linda McClain. The town sits between the Platte River to the south and the Elkhorn River to the north. Both rivers had overflowed their banks, Ms. McClain said. “We’re like an island,” she said. “You cannot get in or out.” Ms. McClain said she spent Saturday visiting shelters where people who had been displaced were congregating. About 75 people had been reluctant to leave their homes, but as the buildings took on water, they were rescued by airboats and taken to the shelters, she said. Many homes were flooded by as much as three or four feet of water. Parts of the city had been under a mandatory evacuation. “Right now, we’re in crisis mode,” she said. Tech. Sgt. Rachelle Blake, of the United States Air Force, said several buildings on the Offutt Air Force Base, which is south of Omaha, had been evacuated as water from Papillion Creek, a tributary of the Missouri River, flooded the southeast part of the base. She said the northwest part of the base was largely unaffected. She said that it was too soon to quantify the damage, but that buildings and hangars were underwater. Aircraft had previously been moved to higher ground. Base personnel and their families were working around the clock to place sandbags and barriers to stop the encroaching floods. “We think it’s going to be another 24 hours before it stops rising,” Sergeant Blake said. It is not unusual for the Midwest to experience spring flooding as ice thaws. But the past week’s widespread devastation was months in the making, as a cold winter left the ground frozen and not absorbent, Mr. Erdman said. Then temperatures rose, melting the snowpack. It also started raining. On Friday, Mr. Ricketts said at a news conference that the flooding was the worst the state had experienced in a half-century. The authorities were still working to handle the situation on Saturday. In addition to the confirmed fatalities, a man whose home near Spencer, Neb., was destroyed when the dam breached was reported missing, according to the authorities. A man in Norfolk, Neb., is also missing. The floodwaters also created new problems. Levees along the Missouri River were breached in two areas near Peru, Neb., prompting authorities to issue warnings of a flash flood, according to the National Weather Service. The Missouri River could rise as water from its tributaries continues to drain, Mr. Erdman said. Nebraska state officials did not say how many homes were damaged or how many people needed rescue. Evacuations were taking place throughout the state, according to the governor’s office. | L21: Relevant | M21: C | N21: =IF(M21="","",IF(M21="A",1,IF(M21="B",0.5,IF(M21="C",0,IF(M21="D",-1,IF(M21="E",0,"")))))) -> 0 | S21: =IF(R21="","",IF(R21="A",1,IF(R21="B",0.5,IF(R21="C",0,IF(R21="D",-1,IF(R21="E",0,""))))))
A22: 197 | B22: 5 | C22: Texas Tornadoes and Central Severe Weather (October 2019) | D22: Severe Storm | E22: 20191020 | F22: 20191020 | G22: IA,IL,IN,KS,MI,MN,MO,ND,NE,OH,OK,SD,TX,WI | H22: https://www.usatoday.com/story/news/weather/2019/10/25/texas-weather-amarillo-hit-rare-october-thundersnow/2453521001/ | I22: Texas weather: Amarillo hit with rare October thunder snow | J22: Oct 25, 2019 ... Texas is no stranger to odd weather. From heat to tornadoes to hail, 2019 has been an eventful year for inclement natural events in the state. | N22: =IF(M22="","",IF(M22="A",1,IF(M22="B",0.5,IF(M22="C",0,IF(M22="D",-1,IF(M22="E",0,"")))))) | S22: =IF(R22="","",IF(R22="A",1,IF(R22="B",0.5,IF(R22="C",0,IF(R22="D",-1,IF(R22="E",0,""))))))
A23: 198 | B23: 3 | C23: California and Alaska Wildfires (Summer-Fall 2019) | D23: Wildfire | E23: 20190601 | F23: 20191130 | G23: AK,CA | H23: https://www.ap.org/news-highlights/best-of-the-states/2019/smoke-from-us-wildfires-boosting-health-risk/ | I23: AP: Smoke from US wildfires boosting health risk for millions | The ... | J23: Jul 5, 2019 ... After last year's deadly wildfires in California brought weeks of sooty skies to cities along the West Coast, the AP decided to take a ... | N23: =IF(M23="","",IF(M23="A",1,IF(M23="B",0.5,IF(M23="C",0,IF(M23="D",-1,IF(M23="E",0,"")))))) | S23: =IF(R23="","",IF(R23="A",1,IF(R23="B",0.5,IF(R23="C",0,IF(R23="D",-1,IF(R23="E",0,""))))))
A24: 204 | B24: 4 | C24: Southeast and Eastern Tornado Outbreak (April 2020) | D24: Severe Storm | E24: 20200412 | F24: 20200413 | G24: AL,CT,DE,FL,GA,KY,MA,MD,ME,MS,NC,NH,NJ,NY,PA,RI,SC,TN,VA,VT,WV | H24: https://www.washingtonpost.com/weather/2020/04/17/tornado-outbreak-satellite-imagery/ | I24: Images from space from Easter Sunday tornado outbreak | J24: Apr 17, 2020 ... ... of the South and Southeast. Three of the tornadoes were deemed ... This map shows the scars from devastating tornadoes that struck eastern ... | N24: =IF(M24="","",IF(M24="A",1,IF(M24="B",0.5,IF(M24="C",0,IF(M24="D",-1,IF(M24="E",0,"")))))) | S24: =IF(R24="","",IF(R24="A",1,IF(R24="B",0.5,IF(R24="C",0,IF(R24="D",-1,IF(R24="E",0,""))))))
A25: 204 | B25: 7 | C25: Southeast and Eastern Tornado Outbreak (April 2020) | D25: Severe Storm | E25: 20200412 | F25: 20200413 | G25: AL,CT,DE,FL,GA,KY,MA,MD,ME,MS,NC,NH,NJ,NY,PA,RI,SC,TN,VA,VT,WV | H25: https://www.washingtonpost.com/weather/2020/04/17/sunday-once-again-features-severe-weather-chances-across-hard-hit-south/ | I25: South faces Sunday severe weather threat for second straight week | J25: Apr 17, 2020 ... Before Easter Sunday's severe weather outbreak, Alabama Gov. Kay Ivey issued an emergency declaration ordering all communities in the state to ... | N25: =IF(M25="","",IF(M25="A",1,IF(M25="B",0.5,IF(M25="C",0,IF(M25="D",-1,IF(M25="E",0,"")))))) | S25: =IF(R25="","",IF(R25="A",1,IF(R25="B",0.5,IF(R25="C",0,IF(R25="D",-1,IF(R25="E",0,""))))))
A26: 212 | B26: 1 | C26: Hurricane Isaias (August 2020) | D26: Tropical Cyclone | E26: 20200803 | F26: 20200804 | G26: CT,FL,MA,NC,NJ,NY,PA,SC | H26: https://www.bostonherald.com/2020/08/03/tropical-storm-isaias-massachusetts-under-a-tropical-storm-watch/ | I26: Tropical Storm Isaias: Massachusetts under a Tropical Storm Watch | J26: Aug 3, 2020 ... ... 2020 at 7:36 PM EDT | UPDATED: August 4, 2020 at 7:01 AM EDT ... Hurricane Isaias. Isaias snapped trees and knocked out power as it ... | N26: =IF(M26="","",IF(M26="A",1,IF(M26="B",0.5,IF(M26="C",0,IF(M26="D",-1,IF(M26="E",0,"")))))) | S26: =IF(R26="","",IF(R26="A",1,IF(R26="B",0.5,IF(R26="C",0,IF(R26="D",-1,IF(R26="E",0,""))))))
A27: 212 | B27: 10 | C27: Hurricane Isaias (August 2020) | D27: Tropical Cyclone | E27: 20200803 | F27: 20200804 | G27: CT,FL,MA,NC,NJ,NY,PA,SC | H27: https://www.usatoday.com/story/news/nation/2020/08/03/tropical-storm-isaias-track-forecast-become-hurricane-carolinas/5571118002/ | I27: Hurricane Isaias track: Storm makes landfall in North Carolina | J27: Aug 4, 2020 ... DURHAM, N.C. – Hurricane Isaias has been downgraded down to a ... Isaias, which prompted evacuation orders in the Tar Heel State over ... | N27: =IF(M27="","",IF(M27="A",1,IF(M27="B",0.5,IF(M27="C",0,IF(M27="D",-1,IF(M27="E",0,"")))))) | S27: =IF(R27="","",IF(R27="A",1,IF(R27="B",0.5,IF(R27="C",0,IF(R27="D",-1,IF(R27="E",0,""))))))
A28: 215 | B28: 17 | C28: Hurricane Sally (September 2020) | D28: Tropical Cyclone | E28: 20200915 | F28: 20200917 | G28: AL,FL | H28: https://www.sunherald.com/news/weather-news/article245765785.html | I28: Scenes from Hurricane Sally in AL, FL, MS Gulf Coast - Sun Herald | J28: Sep 16, 2020 ... As Hurricane Sally slowly swirls along the Gulf Coast, damaging ... — Palmetto State Chasers (@PalmettoChasers) September 15, 2020. | N28: =IF(M28="","",IF(M28="A",1,IF(M28="B",0.5,IF(M28="C",0,IF(M28="D",-1,IF(M28="E",0,"")))))) | S28: =IF(R28="","",IF(R28="A",1,IF(R28="B",0.5,IF(R28="C",0,IF(R28="D",-1,IF(R28="E",0,""))))))
A29: 216 | B29: 9 | C29: Hurricane Delta (October 2020) | D29: Tropical Cyclone | E29: 20201009 | F29: 20201011 | G29: LA | H29: https://www.washingtonpost.com/weather/2020/10/26/zeta-louisiana-florida-flooding/ | I29: Hurricane watches issued for U.S. Gulf Coast as Zeta churns north | J29: Oct 26, 2020 ... Storm is slated to be the 11th named storm to strike the United States in 2020. October 26, 2020More than 5 years ago ... Hurricane Delta hitting ... | K29: Hurricane Zeta intensified overnight and Monday, becoming a hurricane as it drew nearer to Mexico's Yucatán Peninsula. The system is set to pass across the northern Yucatán Monday night before moving into the Gulf of Mexico early Tuesday, and is likely to make landfall along the northern Gulf Coast on Wednesday. High winds, storm surge flooding and torrential rainfall are likely when the storm comes ashore in Louisiana and the Florida Panhandle, with flooding rains possible as far north as the Mid-Atlantic. Hurricane watches were issued Monday afternoon for portions of the Louisiana and Mississippi coastline between Morgan City and the Mississippi-Alabama state border. Farther east, a tropical storm watch is in effect for the Alabama coast and portions of the Florida Panhandle west of the Okaloosa-Walton County line. A tropical storm watch also covers areas west of Morgan City, Louisiana to Intracoastal City. A storm surge watch was also hoisted between Intracoastal City, Louisiana to Navarre, Florida, which includes flood-prone locations like Lake Borgne, Pensacola Bay and Mobile Bay. Most locations will see a 2 to 4 foot surge, but localized spots could see water levels increase by as much as six feet. Zeta is likely to become the 11th named storm to make landfall in the United States this season, setting a record. Only once before has the Greek alphabet been dipped into for names, and that year — 2005 — Zeta was as far as the season went. With another one to three storms possible before the season's conclusion at the end of November, it's conceivable, if not likely, that this year will break 2005′s record for the most storms in an Atlantic hurricane season. Zeta's development also marks yet another storm that's slated to target Louisiana, a storm-weary state that has been hit by a host of weather disasters in 2020. Some parts of the Bayou State have spent a cumulative total of three weeks or more in National Hurricane Center forecast cones in 2020, with Category 4 Hurricane Laura striking in August and Hurricane Delta hitting in October. Although Zeta's incipient landfall midweek doesn't look to be overly intense, it's another hit for a state struggling to cope with multiple simultaneous recovery efforts amid a worsening coronavirus pandemic. "Hurricane conditions and life-threatening storm surge are possible along portions of the northern Gulf Coast on Wednesday," wrote the National Hurricane Center. Where Hurricane Zeta is now At 5 p.m. Monday, Zeta had winds of 80 mph — just over the threshold of hurricane strength. It was moving northwest at 10 mph, and is set to pass over the northern Yucatán Peninsula late Monday and Monday night, where hurricane warnings are in effect between Tulum and Dzilam, as well as for Cozumel. The resort cities of Playa del Carmen and Cancun, both heavily impacted by Hurricane Delta two weeks ago, will be affected, as well. Emergence over the Gulf on Tuesday During its encounter with land, Zeta — which at landfall will probably still be a Category 1 hurricane — will weaken some before reemerging over the Gulf of Mexico. There are conflicting signals for the extent to which Zeta will be able to reorganize. The most likely scenario is a maintenance of strength or slow weakening as it approaches the Louisiana coast as a high-end tropical storm or Category 1 hurricane. At the lowest levels, minimal ocean heat content, or the energy that warm ocean waters can contribute to the maintenance or intensification of tropical systems, is present. Sea surface temperatures, while milder than average for this time of year, have decreased following recent cold fronts, with little recovery. In the upper atmosphere, high pressure and broad clockwise flow over the Gulf of Mexico will help with Zeta's outflow, or the evacuation of already spent air exiting from the storm's center, which could help it maintain strength longer than normal over otherwise less-than-ideal sea surface temperatures. Mid-level winds may become more disruptive as the circulation approaches the coast Wednesday, inducing some weakening. Forecast for Louisiana and Mississippi Conditions will deteriorate in Louisiana and Mississippi on Wednesday morning. The brunt of the storm's high winds, coastal flooding and heavy rains occur during the evening as Zeta moves northward ahead of an approaching storm from the west. This means Zeta will be accelerating north and northeastward, its inclement weather arriving considerably faster than during hurricanes Laura and Delta. Strong wind gusts near the coast could potentially top 70 mph, while storm surge flooding could affect a large area from where the storm makes landfall eastward into Mississippi, Alabama and Florida. Heavy rain is likely, too, with pockets of six inches or more likely from the greater New Orleans area into southern Mississippi and southwest Alabama. Heavy rain in the Southeast, Mid-Atlantic There are also growing signs that Zeta's moisture will interact with a stalled cold front that will be draped across the eastern United States, depositing a strip of heavy rainfall in the Southeast and perhaps the southern Mid-Atlantic late this week. Atlanta could be drenched with several inches of rain, prompting a flash flood watch to be issued, while a good soaking is possible in the Carolina Piedmont. Confidence is also increasing in very wet weather overspreading the Washington to New York City corridor, as a mid-latitude storm and the remnant moisture of Zeta combine to produce heavy downpours. However, there still remains uncertainty in whether those two pieces will come together, and it remains possible that the heaviest rain skirts or misses D.C. Meanwhile, hurricane season doesn't look to be over quite yet. Meteorologists have been concerned for weeks that the start of November could feature another flurry of storminess as a large-scale shift in the upper atmosphere becomes more conducive to generating tropical systems in the Atlantic. That looks to last for, perhaps, the first half of the month. If we wind up with one more storm, we'll tie the record for most observed in a season (2005 had one unnamed storm in addition to Zeta); two more, and we'll beat it. And in a year like 2020, just about anything is possible. | L29: Trash | N29: =IF(M29="","",IF(M29="A",1,IF(M29="B",0.5,IF(M29="C",0,IF(M29="D",-1,IF(M29="E",0,"")))))) | S29: =IF(R29="","",IF(R29="A",1,IF(R29="B",0.5,IF(R29="C",0,IF(R29="D",-1,IF(R29="E",0,""))))))
A30: 220 | B30: 11 | C30: Western/Central Drought and Heat Wave (Summer-Fall 2020) | D30: Drought | E30: 20200601 | F30: 20201230 | G30: AK,AZ,CA,CO,HI,IA,ID,IL,IN,KS,MI,MN,MO,MT,ND,NE,NM,NV,OH,OK,OR,SD,TX,UT,WA,WI,WY | H30: https://www.washingtonpost.com/weather/2020/09/02/california-heat-wave-wildfires/ | I30: Extreme heat wave targets California as wildfires rage | J30: Sep 3, 2020 ... One way to look at how volatile the fire weather conditions are in California, and how the upcoming heat wave could put parts of the state back ... | N30: =IF(M30="","",IF(M30="A",1,IF(M30="B",0.5,IF(M30="C",0,IF(M30="D",-1,IF(M30="E",0,"")))))) | S30: =IF(R30="","",IF(R30="A",1,IF(R30="B",0.5,IF(R30="C",0,IF(R30="D",-1,IF(R30="E",0,""))))))
A31: 220 | B31: 12 | C31: Western/Central Drought and Heat Wave (Summer-Fall 2020) | D31: Drought | E31: 20200601 | F31: 20201230 | G31: AK,AZ,CA,CO,HI,IA,ID,IL,IN,KS,MI,MN,MO,MT,ND,NE,NM,NV,OH,OK,OR,SD,TX,UT,WA,WI,WY | H31: https://www.npr.org/2020/08/17/903291108/heat-wave-causes-power-outages-in-california | I31: Heat Wave Causes Power Outages In California - NPR | J31: Aug 17, 2020 ... A heat wave in the West is causing rolling power outages in parts of California. And many places where people usually go to cool off — such as ... | K31: A heat wave in the West is causing rolling power outages in parts of California. And many places where people usually go to cool off — such as theaters and malls — are closed due to the pandemic. LEILA FADEL, HOST: A heat wave in the West is causing rolling blackouts in California. Here's Jeff Smith with California's largest utility Pacific Gas and Electric. JEFF SMITH: We are encouraging our customers to conserve as much energy as possible over the course of the next few days because we do anticipate that this heat wave is going to continue. FADEL: Here to talk about this is Lily Jamali from member station KQED in San Francisco. Welcome. LILY JAMALI, BYLINE: Thanks, Leila. FADEL: So Lily, how widespread are these blackouts? JAMALI: Well, millions of Californians were told on pretty short notice to brace for these power outages. This weekend, on PG&E's territory alone in the north of the state, around a quarter-million people actually lost power, first on Friday evening then again on Saturday. And it really caught people by surprise. California hasn't experienced this type of outage since the 2001 energy crisis. We got a brief reprieve yesterday, but we're all bracing ourselves to see what happens tonight. FADEL: So what's going on? Is it just the heat, or are there other factors at play? JAMALI: Well, the heat wave is definitely a huge part of this and will be through the middle of this week. Because it's been so hot with temperatures setting records up and down the state, people are using a lot of power right now to stay cool. In California, there's a nonprofit called the ISO that operates most of the grid. And what they saw was demand for electricity getting dangerously close to what power plants were producing. So with that supply-demand mismatch, they directed the utilities to start shutting off power to parts of their systems. And just to be clear, this is different from the power shutoffs aimed at preventing fires. We had a bunch of those last year. There, it's the utilities making the call. Here, they're being told what to do to ensure that the whole system doesn't crash. And when you get a system-wide failure, it can take a lot longer - sometimes days - to recover from. That's what officials are trying to prevent. FADEL: So how are our elected officials responding to the blackouts? JAMALI: Well, for one thing, Gov. Gavin Newsom is calling for an investigation into what happened this weekend. Energy politics brought down another governor almost two decades ago. Gray Davis faced a recall in part because of blackouts then, and Newsom is well aware of that. He is calling a state of emergency and said it was unacceptable that people didn't have enough time to prepare. Meanwhile, the manager of the state grid is holding a linchpin of the energy market here, a bidding system that involves buying and selling power ahead of time. Critics say that system can cause wild fluctuations in price and lead to shortages. FADEL: So what are residents doing now that these blackouts are happening or are threatening to happen? JAMALI: Yeah. Well, conservation is really key right now. Utilities are asking people to raise their thermostats to 78 degrees. Basically, they just want people to use less power if they can, especially when demand spikes in the late afternoons. The problem is there aren't many places to go to cool off right now. Because of the pandemic, places like malls and movie theaters pose a health risk even if they are open, same with many cooling centers. And we're not congregating in big office buildings where the air conditioner is blasting. Many people are working from home, so the AC is blasting there if they have it. And so what you have is an already dicey situation getting a lot more complicated because of the pandemic. FADEL: That's reporter Lily Jamali with member station KQED in San Francisco. Thank you so much. JAMALI: Thank you. | N31: =IF(M31="","",IF(M31="A",1,IF(M31="B",0.5,IF(M31="C",0,IF(M31="D",-1,IF(M31="E",0,"")))))) | S31: =IF(R31="","",IF(R31="A",1,IF(R31="B",0.5,IF(R31="C",0,IF(R31="D",-1,IF(R31="E",0,""))))))
A32: 221 | B32: 1 | C32: California Flooding and Severe Weather (January 2021) | D32: Flooding | E32: 20210124 | F32: 20210129 | G32: CA | H32: https://www.marinij.com/2021/02/03/ross-valley-flood-project-draft-eir-flags-park-impact/ | I32: Ross Valley flood project draft EIR flags park impact | J32: Feb 3, 2021 ... PUBLISHED: February 3, 2021 ... A scaled-back version of a $14 million effort to curb flooding in the ... California Department of Water Resources ... | K32: A scaled-back version of a $14 million effort to curb flooding in the Ross Valley could spare more than 100 trees in a creekside park, but would leave residents vulnerable to overtopping waters, a new report finds. A draft environmental impact report, released Monday, concludes that the Corte Madera Creek flood risk management project as proposed would result in aesthetic impacts in Frederick Allen Park in Ross once the trees come down. The report identifies 56 potential adverse environmental impacts, 19 of which are considered significant but could be offset by extra steps taken during construction. The report presents four alternative plans, including a no-project option, as well as “alternative 1” — the only option that would avoid tree removal within the park. The loss of the trees has been a point of contention for some in the neighborhood. “However, in a 100-year storm event, Alternative 1 would have less flood reduction benefit and would result in increased water surface elevation compared to the proposed project, particularly along Poplar Avenue,” the report finds. Residential and commercial areas around the park also would also have less flood reduction benefits, the report notes. The project aims to reduce the frequency and severity of flooding in Ross and Kentfield, offering increased 25-year flood protection and improved fish passage and habitat through the creek channel, as well as some recreational enhancements. The existing proposal calls for the removal of a fish ladder and a concrete channel from Frederick Allen Park, which runs along the creek between Sir Francis Drake Boulevard and Poplar Avenue. It also calls for restoring the natural channel, installing taller floodwalls and a new stormwater pump station in the Granton Park neighborhood, creating larger fish resting pools and removing the concrete channel from Stadium Way to improve the natural fish and wildlife habitat. As part of the project, 113 to 144 trees would have to be removed. New trees would be planted, taking an estimated 10 years to mature, according to the report. “We will work towards removing the least number of trees possible while still meeting the project goals,” Joanna Dixon, a Marin County Flood Control and Water Conservation District engineer and project manager. The report says the existing proposal could result in some increased flooding risk in parking areas near the College Avenue bridge, but no homes or businesses would be threatened. “The big message is that it won’t eliminate all flooding — that would be cost prohibitive,” Dixon said. “The key is finding the sweet spot of maximum flood reduction and minimum project cost and impact to the adjacent area.” Even though alternative 1 would avoid cutting down the trees, the U.S. Army Corps of Engineers might still require some trees be removed since the project is making improvements to the concrete channel that the Army Corps built in the 1960s. Under its guidelines, the corps could require trees within 15 feet of the creek’s floodwall to be removed at any time, with or without a project. Alternative 1 would also add four larger fish resting pools near the park to improve fish passage. The rest of the project would remain as proposed. Alternatives 2 and 3 would require the same number of trees to be removed as the proposed project. Alternative 2 would call for the addition of a boardwalk bike path in Frederick Allen Park. The path would be elevated above the floodplain. The rest of the project elements would remain as proposed. Alternative 3 would use rock and other natural materials to reduce the use of concrete. “It is important to move forward, so any of the alternatives except for the no-project alternative, would be an improvement,” Sandra Guldman, president of the Friends of Corte Madera Creek Watershed, who said her organization is taking time to review the document to submit a formal response. Guldman said she believes the proposed project offers the best flood protection and habitat restoration. Consideration of benefits to Ross should be secondary to the goal of the project, she added. Ross Town Councilwoman Julie McMillan said the aesthetics of the park are important to the community. “The project changes the visual quality of the park by removing more than 100 established trees during the construction phase,” she said. “It will be important that the park remains appealing to users of all ages by planting sufficient trees and landscaping to provide visual interest and shade. “Consideration should be given to the long-term aesthetic quality of the park as well as the interim period while newly planted vegetation is becoming established,” she said. The Town Council will discuss the draft EIR at its meeting on Feb. 11. Information will be posted at townofross.org. Marin County Supervisor Katie Rice, whose District 2 includes the Ross Valley, said, “The project has evolved in scope and design in response to community and town input, environmental and regulatory concerns. So, really exciting to finally have the draft EIR out for public review and comment.” The project was led in partnership with the U.S. Army Corps of Engineers until March 2019, when the county moved to manage the project locally. It is being funded with money from the Ross Valley Flood Control Zone 9 storm drainage fee and grants from the California Department of Water Resources, the State Coastal Conservancy Proposition 1 and other sources. The county is collecting comments on the draft EIR through March 17. Comments can be emailed to the project team at cortemaderacreek@marincounty.org or mailed to Dixon at P.O. Box 4186, San Rafael, 94913. A public hearing via teleconference is set for the Board of Supervisors meeting on March 2. Information is at bit.ly/2MWbh6v. | N32: =IF(M32="","",IF(M32="A",1,IF(M32="B",0.5,IF(M32="C",0,IF(M32="D",-1,IF(M32="E",0,"")))))) | S32: =IF(R32="","",IF(R32="A",1,IF(R32="B",0.5,IF(R32="C",0,IF(R32="D",-1,IF(R32="E",0,""))))))
A33: 222 | B33: 7 | C33: Northwest, Central, Eastern Winter Storm and Cold Wave (February 2021) | D33: Winter Storm | E33: 20210210 | F33: 20210219 | G33: CT,DE,FL,GA,IA,ID,IL,IN,KS,MA,MD,ME,MI,MN,MO,MT,NC,ND,NE,NH,NJ,NY,OH,OK,OR,PA,RI,SC,SD,TX,VA,VT,WA,WI,WV | H33: https://www.npr.org/2021/02/16/968293872/winter-storm-not-over-yet-for-much-of-the-country | I33: Winter Storm Is Not Over Yet For Much Of The Country - NPR | J33: Feb 16, 2021 ... Heavy snowfall and frigid temperatures across the U.S. have kept winter storm warnings in effect from Washington to the Great Lakes into ... | K33: Heavy snowfall and frigid temperatures across the U.S. have kept winter storm warnings in effect from Washington state to the Great Lakes into northern New England and a large section of the South that includes Texas, Oklahoma, Louisiana and Arkansas. It's also left more than four million customers without power across the United States, including three million in Texas alone. The record-breaking cold weather has claimed 16 lives so far, "including three people found dead after a tornado hit a seaside town in North Carolina and four family members who perished in a Houston-area house fire while using a fireplace to stay warm," the Associated Press reported. Others have died in car crashes caused by dangerous road conditions and from carbon monoxide poisoning. "The major winter storm responsible for producing significant snow and ice accumulations in parts of the central and eastern U.S. the last couple days is making a beeline for eastern Canada, but not before it causes heavy snow and freezing rain in parts of the eastern Great Lakes and New England," NOAA's Weather Prediction Center said early Tuesday. "[The] Arctic high pressure over the Heartland will ensure one more day of frigid temperatures east of the Rockies and west of the Appalachians. Numerous record cold maximum and minimum temperatures are expected today with the bulk of them occurring in the South Central U.S. where daily anomalies range between 35 to 45 degrees below normal," it added. Here's a sampling of conditions around the country: South President Biden approved a state of emergency declaration for Texas following a request from Gov. Greg Abbott on Sunday, as the state began enduring some of the lowest temperatures in 30 years. Making matters worse, continuing power outages that began on Monday have left more than 3 million customers in the dark and cold, with temperatures expected to plummet to as low as -5. As NPR reported, that has prompted the governor to pursue an overhaul of the group that manages the state's power grid during the legislature's current session. Meantime, however, officials have requested 60 generators from the Federal Emergency Management Agency, to continue running heat into hospitals and nursing homes, according to the AP. The state has also opened 35 shelters to house more than 1,000 people, the agency said. The Electric Reliability Council of Texas, or ERCOT, issued a notice on its website advising customers that rolling blackouts had been "significantly extended due to the current emergency grid conditions and severe cold weather." Northern Texas was likely experiencing its most severe cold snap so far this century, according to member station KERA in Dallas. "I've seen snow. I've seen it get bad, [but] ... I don't think I've seen the temperatures like we're going to see this week," Trace Magee told the public radio station. The NWS in Fort Worth issued a warning for residents in and around the Fort Worth area telling them to expect "a crippling amount of ice and sleet." In Tennessee, three people have died due to the weather and the state's Department of Transportation says it's "working around the clock to clear roads, ice and snow caused multiple wrecks on interstates and countless cars have gotten stuck or slid off of side roads," News Channel 5 in Nashville reported. Parts of Mississippi are experiencing unusually cold temperatures. Throughout Oklahoma, the National Weather Service has warned of wind chill temperatures of -25 and snow accumulation of 4 to 8 inches through Wednesday. By 5 p.m. local time Tuesday evening temperatures had dropped as low as 11 degrees, which was driving up natural gas demands and causing outages in some regions. The situation became so dire that Gov. Kevin Stitt reached out to President Biden by phone. "I asked him to help Oklahomans with the substantial increase in energy bills that will likely be coming our way and he pledged his support," Stitt said in a tweet. During a call-in appearance on local news station KOCO 5, Stitt broke down the various sources of heat warming people's homes and businesses. "We are not getting the wind, some of the stuff is frozen, we've got ice on the propellers," Stitt said. "There is zero solar right now. Thank goodness we have coal, 46% of our generation right now is coal. Natural gas, we have some pipes that have been freezing. So only 28% of electricity have been generated by natural gas. Hydro, that's about 6%, that's water." Arkansas was expecting record low temperatures down to -13 in the northwestern Fayetteville area and snowfall from 6 to 10 inches in the central part of the state. Louisiana Gov. John Bel Edwards said in a Zoom call with media late Monday that the state could experience rolling blackouts due to electricity demands. Northwest In Washington state, a forecast of warmer temperatures later in the week has prompted concern of flooding as the heavy snowfall melts. Washington State Patrol said they responded to 861 car collisions from Friday through Sunday. Still, the rare winter storm, which dumped about a foot of snow over Seattle, did not deter a 90-year-old woman from walking six miles round-trip for her first coronavirus vaccine shot on Sunday morning, the Seattle Times reported. Midwest In Chicago, where more than two feet of snow was already on the ground, up to 16 additional inches was added near Midway Airport by early Tuesday. The city's famous lake effect weather will move into northwest Indiana as the day wears on, according to CBS Channel 2. At least four buildings have collapsed in Chicago in recent days due to snow build-up that caused roofs to cave in, according to the Chicago Tribune. Gov. JB Pritzker on Tuesday issued a disaster proclamation after the storm to open up resources. "We're using all resources at our disposal to keep our communities safe amid this dangerous winter weather. And working with local governments as well as our federal partners to protect ratepayers from soaring utility bills," Pritzker said on Twitter. He added: "I urge everyone to take this extreme weather seriously." The northeast Indiana city of Fort Wayne was digging out Tuesday morning from what local media described as the largest recorded snowfall for Feb. 15. A winter storm warning had been in effect for a band of northern Ohio that skirts Lake Erie. However, early Tuesday, the National Weather Service canceled warnings for the Upper Ohio Region. Even so, in Cleveland, sleet and freezing rain on the roads were complicating the morning commute Tuesday, ABC News 5 reports. New England Another unbroken swath of warnings extends through the northern sections of Pennsylvania, New York, Vermont, New Hampshire and Maine. In Albany, however, residents were expecting warmer temperatures would begin burning off the mix of freezing rain and snow that had fallen overnight. In northern Vermont, a winter storm warning remains in effect until Tuesday evening, with up to 4 more inches of snow expected throughout the day. Parts of Maine are preparing for snow totals of 6 to 10 inches overnight with areas in the northern portion of the state expecting another foot or more. "We should see a couple of dry days before another winter storm Thursday night into Friday. That storm also will have heavy snow for the mountains and ice or snow for the coast," ABC affiliate, WMTW News cautioned viewers. | N33: =IF(M33="","",IF(M33="A",1,IF(M33="B",0.5,IF(M33="C",0,IF(M33="D",-1,IF(M33="E",0,"")))))) | S33: =IF(R33="","",IF(R33="A",1,IF(R33="B",0.5,IF(R33="C",0,IF(R33="D",-1,IF(R33="E",0,""))))))
A34: 227 | B34: 1 | C34: Southern Tornadoes and Southeast Severe Weather (May 2021) | D34: Severe Storm | E34: 20210502 | F34: 20210504 | G34: AL,AR,FL,GA,KY,LA,MS,NC,OK,SC,TN,TX,VA,WV | H34: https://www.cnn.com/2021/05/04/weather/tornadoes-severe-storms-forecast-tuesday | I34: Severe weather risk raised in US Southeast amid multiday threat of ... | J34: May 4, 2021 ... A tornado watch was issued Tuesday for over 4 million people from eastern Louisiana through southeastern Mississippi, much of southern Alabama ... | K34: The risk of severe thunderstorms was raised to a Level 4 out of 5 in parts of Mississippi and Alabama amid a multiday storm outbreak that has already killed three people. In all, nearly 100 million people stretching from the Gulf Coast up to New England could see severe weather on Tuesday, defined as a storm that produces a tornado, damaging winds or large hail, according to the Storm Prediction Center. The Level 4 “moderate” threat is in place for 1 million people in Mississippi and Alabama; the Level 3 “enhanced” threat affects about 6.5 million from Louisiana to Georgia; and the Level 2 “slight” threat affects 32 million people in the Southeast, lower Ohio Valley and mid-Atlantic, the center said. On Sunday, tornadoes struck at least three Mississippi cities, and on Monday tornado and thunderstorm watches stretched from Mississippi to south-central North Carolina, including the metro Atlanta area, where a tornado touched down and caused widespread damage. Two people in Georgia died Monday and one person in Tennessee died Tuesday, all from falling trees. A tornado watch was issued Tuesday for over 4 million people from eastern Louisiana through southeastern Mississippi, much of southern Alabama and a small portion of the Florida Panhandle. The watch includes Hattiesburg, Mississippi, and Tuscaloosa and Montgomery in Alabama and is in place until 10 p.m. CT. A flash-flood emergency has been issued for southeastern Jefferson County and northwestern Shelby County in central Alabama, according to the National Weather Service (NWS). This includes Birmingham, Hoover, Bessemer and other areas of the Birmingham metro. The NWS says flooding is ongoing after 3 to 5 inches of rain fell this afternoon. Rain is continuing and an additional one to two inches is possible before the rain comes to an end later this evening. As Tuesday progresses, the heat and humidity that accompanies the month of May in the Deep South will help to reinvigorate the atmosphere. Areas along the Gulf Coast, from East Texas to the Florida Panhandle, could see strong to severe storms pop up until the arrival of the severe gusts that come with the advancing front. Areas from Central Louisiana, Alabama, Georgia, and Mississippi are more likely to see impacts from hail and damaging straight-line winds rather than tornadoes. But tornadoes are still possible. In all, just over 90 million people could experience severe weather Tuesday. Three dead in Georgia and Tennessee The region is still reeling from weather that killed two people in Georgia and one person in Tennessee. A Houston County, Georgia, resident died as a result of the weather that struck Monday, the Houston County Emergency Management Agency said in a news release. The 55-year-old woman was killed by a falling tree. “When Fire Department crews arrived, they found a large pine tree had fallen into the living room area of the home causing substantial damage to the roof and outer walls. Tragically crews also discovered that Mrs. Carla Harris, 55, was struck by the falling tree and sustained fatal injuries,” according to the news release from the Houston County Emergency Management Agency. More than 100 miles away, a man in Douglasville, Georgia, was killed after a tree fell on his car as a tornado touched down Monday. The Douglas County Fire Department responded to reports of a tree on a car with a person inside around 10:36 a.m., according to a news release from county officials. “When they arrived on the scene, they discovered the driver trapped inside the vehicle with power lines and a tree on the vehicle,” Douglas County communications director Rick Martin said in the release. “Firefighters had to extricate the driver who we are only identifying as a male at this time until next of kin are notified.” In Weakley County, Tennessee, a 49-year-old woman died when a tree fell on the home where she was sleeping Tuesday morning, according to Dresden Police Chief Christopher Crocker. Crocker said what appears to be a powerful straight-line wind came through a trailer court around 4 a.m. ET and took down a number of trees. Three mobile homes total were hit, according to Crocker, and there were other victims with minor injuries. Crocker said there have been no reports of a tornado touchdown, but severe thunderstorms have left behind “extensive damage” such as downed power lines and trees and flipped trailers. Days of rain could mean flash flooding Many states across the Southeast have seen double their normal rainfall over the last month, so even 1 to 2 inches of additional rain could lead to flash flooding. Flash flooding will be possible across the South thanks to the combination of heavy rainfall and all the rain that has fallen in recent days and weeks. A widespread 1-3 inches of rain is forecast across this region into Tuesday night. “Large hail, damaging wind gusts and a few tornadoes will be likely along with rainfall rates in excess of an inch per hour,” said the National Weather Service office in Jackson, Mississippi. Rounds of thunderstorms and rain showers will traverse across the Ohio and Tennessee River Valleys throughout the day Tuesday. Farther south, scattered storms will likely develop midday from eastern Texas through Georgia. This line of storms should weaken by Wednesday morning as it approaches the East Coast, but isolated severe weather will remain possible. | N34: =IF(M34="","",IF(M34="A",1,IF(M34="B",0.5,IF(M34="C",0,IF(M34="D",-1,IF(M34="E",0,"")))))) | S34: =IF(R34="","",IF(R34="A",1,IF(R34="B",0.5,IF(R34="C",0,IF(R34="D",-1,IF(R34="E",0,""))))))
A35: 239 | B35: 16 | C35: Western Wildfires (2021) | D35: Wildfire | E35: 20210601 | F35: 20211231 | G35: AK,AZ,CA,CO,HI,ID,MT,NM,NV,OR,UT,WA,WY | H35: https://www.latimes.com/california/story/2021-06-26/drought-wildfire-conditions-evolving-at-unprecedented-pace | I35: California's drought and wildfire dangers rising at stunning pace | J35: Jun 26, 2021 ... The current drought, which blankets the entire state and a broad swath of the western United States, according to the U.S. Drought Monitor, is ... | N35: =IF(M35="","",IF(M35="A",1,IF(M35="B",0.5,IF(M35="C",0,IF(M35="D",-1,IF(M35="E",0,"")))))) | S35: =IF(R35="","",IF(R35="A",1,IF(R35="B",0.5,IF(R35="C",0,IF(R35="D",-1,IF(R35="E",0,""))))))
A36: 242 | B36: 4 | C36: Southern Tornado Outbreak (March 2022) | D36: Severe Storm | E36: 20220330 | F36: 20220330 | G36: AL,AR,FL,GA,KY,LA,MS,NC,OK,SC,TN,TX,VA | H36: https://dailyleader.com/2022/03/31/severe-storms-pummel-south-killing-at-least-2-in-florida/ | I36: Severe storms pummel South killing at least 2 in Florida | Daily Leader | J36: Mar 31, 2022 ... The worst of the weather Thursday morning appeared to be at the southern ... severe weather blew through during a tornado warning Wednesday ... | K36: A line of severe storms packing isolated tornadoes and high winds ripped across the Deep South overnight — killing at least two in the Florida Panhandle, toppling trees and power lines and leaving homes and businesses damaged as the vast weather front raced across several states. In Florida, the Washington County Sheriff’s Office said Thursday morning that two were killed and two injured when a tornado touched down in the western Florida Panhandle. Two homes were destroyed and powerlines were knocked down, according to Washington Country Emergency Management spokeswoman Cheryl Frankenfield. The county’s Facebook page showed at least one home that was obliterated, as well as trees down on another home. No other details were immediately available. The Florida Division of Emergency Management has employees in the area to help, spokesperson Samantha Bequer said. She said neighboring Jackson County also had property damage. “It’s a nasty day, but thankfully these storms are moving quickly,” she said. At least two confirmed tornadoes injured several people Wednesday, damaged homes and businesses and downed power lines in Mississippi and Tennessee after earlier storm caused damage in Arkansas, Missouri and Texas. About 185,000 customers were without electricity Thursday morning in the wake of the storm along a band of states: Mississippi, Alabama, Tennessee, Kentucky, Indiana, Ohio and Michigan, according to poweroutage.us, which tracks utilities. The worst of the weather Thursday morning appeared to be at the southern end of the storm front, which was expected to bring heavy rain and high winds all along the U.S. East Coast later in the day. Much of the Florida Panhandle was under a tornado watch, according to the National Weather Service in Tallahassee. Widespread damage was reported in the Jackson, Tennessee, area as a tornado warning was in effect. “Significant damage” occurred to a nursing home near Jackson-Madison County General Hospital and the Madison County Sheriff’s Office in Jackson, said Madison County Emergency Management Director Jason Moore. In Nashville, Tennessee, paneling fell five stories from the side of a downtown hotel Wednesday evening and onto the roof of a building below. The fire department warned that debris could become airborne as high winds continued, and some hotel guests were moved to other parts of the building due to concerns the roof would become unstable. No injuries were immediately associated with the collapse. Daylight revealed widespread wind damage across Alabama. One person was hurt when a storm hit the University of Montevallo campus south of Birmingham, damaging a dormitory, officials said, and a woman was injured when a manufactured home rolled over in rural Bibb County. A school bus was flipped at a high school in south Alabama, and part of the roof was missing from a church in northwest Alabama. Elsewhere, a warehouse roof collapsed as the storms moved through Southaven, Mississippi, near Memphis, police said. The building had been evacuated and no injuries were reported. The Mississippi Senate suspended its work Wednesday as weather sirens blared during a tornado watch in downtown Jackson. Some employees took shelter in the Capitol basement. Rander P. Adams said he and his wife, Janice Delores Adams, were in their home near downtown Jackson when severe weather blew through during a tornado warning Wednesday afternoon. He said their lights flashed and a large window exploded just feet from his wife as she tried to open their front door. “The glass broke just as if someone threw a brick through it,” he said. “I advised her then, ‘Let’s go to the back of the house.'” Adams said the storm toppled trees in a nearby park, and a large tree across the street from their house split in half. “We were blessed,” he said. “Instead of falling toward the house, it fell the other way.” Earlier Wednesday, a tornado that struck Springdale, Arkansas, and the adjoining town of Johnson, about 145 miles northwest of Little Rock, shortly after 4 a.m. injured seven people, two critically, according to Springdale Mayor Doug Sprouse. Sprouse said in a statement that one of those critically injured had improved and was in stable condition and the other five were released from a hospital. “Our first responders have completed door-to-door searches, and we believe everyone has been accounted for,” Sprouse said. The National Weather Service in Tulsa said Thursday that the tornado has been rated an EF-3, up from an initial assessment of EF-2, with wind speeds between 136-165 mph. The tornado reached a peak speed of about 145 mph and 5 miles while on the ground for about eight minutes, according to the weather service. In northwest Missouri, an EF-1 tornado with wind speeds around 90 mph struck St. Joseph on Tuesday night, damaging two homes. A small tornado also touched down briefly on the eastern edge of Dallas, according to the National Weather Service in Fort Worth. The tornado struck just after 4:30 a.m. Wednesday near McClendon-Chisolm with top winds of about 100 mph and damaged homes, but no injuries were reported, according to the weather service. The storms come a week after a tornado in a New Orleans-area neighborhood carved a path of destruction during the overnight hours and killed a man. Strong winds in Louisiana overturned semitrailers, peeled the roof from a mobile home, sent a tree crashing into a home and knocked down power lines, according to weather service forecasters, who did not immediately confirm any tornadoes in the state. The National Weather Service office in New Orleans said Thursday that teams would be out in Tangipahoa and St. Tammany Parishes in southeastern Louisiana and in Jackson County in southeastern Mississippi surveying damage. They said the highest wind speed recorded in the office’ coverage area was 67 mph at the New Orleans Lakefront airport with winds in Baton Rouge reaching into the high 50 mph range. Firefighters, meanwhile, have been trying to get handle on a wildfire spreading near Great Smoky Mountains National Park in Tennessee, amid mandatory evacuations as winds whipped up ahead of the approaching storm front. The fire, which was not contained, had expanded to about 250 acres as of Wednesday afternoon. One person was injured, and a plume of smoke rose above one community not far from where 2016 wildfires ravaged the tourism town of Gatlinburg, killing 14 people and damaging or destroying about 2,500 buildings. | N36: =IF(M36="","",IF(M36="A",1,IF(M36="B",0.5,IF(M36="C",0,IF(M36="D",-1,IF(M36="E",0,"")))))) | S36: =IF(R36="","",IF(R36="A",1,IF(R36="B",0.5,IF(R36="C",0,IF(R36="D",-1,IF(R36="E",0,""))))))
A37: 252 | B37: 3 | C37: Kentucky and Missouri Flooding (July 2022) | D37: Flooding | E37: 20220726 | F37: 20220728 | G37: KY,MO | H37: https://www.npr.org/2022/07/29/1114417118/because-of-climate-change-inland-flooding-is-becoming-more-common | I37: Because of climate change, inland flooding is becoming more ... - NPR | J37: Jul 29, 2022 ... The floods in Missouri and Kentucky this week were both caused by extreme rainfall ... So heavy rain has increased all over the U.S. And in the ... | K37: ASMA KHALID, HOST: Climate change is making these types of disasters more and more common. I spoke with Rebecca Hersher from NPR's climate team, and she explained why destructive flooding is happening far from the coastlines. REBECCA HERSHER, BYLINE: There are many ways that climate change can cause floods. Coastal floods get a lot of attention, especially when they happen during a hurricane. But actually, inland flooding is more common. And the kind of devastating heavy rain that we've seen this week is something that climate scientists have predicted for many decades - that, as humans keep burning fossil fuels, the atmosphere gets hotter, the air holds more moisture and so, when it rains, it rains harder. KHALID: And has that turned out to be true? HERSHER: Yeah, the climate models are correct. And actually scientists can observe it in real time now, which is pretty scary. So heavy rain has increased all over the U.S. And in the southeastern U.S., including in Kentucky, it's increased by almost a third. KHALID: Wow. HERSHER: Now, that might not sound like a lot, but an extra inch of rain, if you think about it - if that falls in a short period of time, that is how you get a flash flood. KHALID: So explain that because I do think it is shocking to see some of the damage that all of this rain has caused, particularly in Kentucky, as you mentioned. HERSHER: Yeah. The danger and the damage comes from moving water, and that can happen in two ways. So first, when a lot of rain is falling in a short period of time, the water doesn't have anywhere to go. It can't soak into the ground, especially if the ground is already saturated. So that causes the water to pool on the surface. And then if there's a hill - even a really small hill, one that you might not even notice - all that water starts to roll downhill. It gathers speed, it gathers power, it can pick up debris. And that is a flash flood. It's really dangerous. It can carry away cars, it can carry away houses, and it can kill people. KHALID: So how common is that type of flooding? You know, you said it is getting more frequent at this point. HERSHER: Yeah. And unfortunately, these kinds of floods, they're so frequent that they're a part of life in some places. So there are towns and cities in the U.S. where flash floods happen every year or every other year. That's true in parts of southeast Texas and Louisiana, parts of the Midwest and Appalachia, where this week's floods happened. For example, last summer, there was a flash flood that killed nearly two dozen people in Tennessee. That same area was hit by very heavy rain this year. And it's important to say, this is not just a U.S. problem. It's happening outside the U.S. as well. So heavy rain has caused deadly flash floods in Germany and Belgium, South Africa, India, China and Australia. And that's just in the last year. KHALID: So what can be done to warn people when a flood is about to happen? HERSHER: Well, that's actually something the National Weather Service is really focused on. So local offices are watching for signs of heavy rain and then trying to warn people as early as possible if a flash flood is likely. And that's really important because so many of us get our weather warnings now directly on our phones, right? Your phone will flash and you'll get an alert saying there's a flash flood warning for your area. And if that happens, you need to take it extremely seriously. And particularly, don't drive on flooded roads. It's one of the main ways that people die in flash floods. Their cars just get swept away. KHALID: So, I mean, I've got to wonder, are there ways to make these floods less dangerous, or do we all sort of have to learn to live with this new reality? HERSHER: There are lots of ways to make them less dangerous. So basically, you slow the water down, give it safe places to go. For example, have less pavement so the water can soak into the ground. You can build retention ponds - you know, those low marshy areas for excess water to collect. KHALID: Right. HERSHER: And in cities, you can make the pipes bigger. So a lot of U.S. cities were built 50, even 100 years ago. The storm water systems are not built for the heavy rain of today. It's expensive to make those pipes larger, but it's really important if you want to prevent streets from turning into rivers. KHALID: Rebecca Hersher from NPR's climate team, thanks, as always. HERSHER: Thanks. | N37: =IF(M37="","",IF(M37="A",1,IF(M37="B",0.5,IF(M37="C",0,IF(M37="D",-1,IF(M37="E",0,"")))))) | S37: =IF(R37="","",IF(R37="A",1,IF(R37="B",0.5,IF(R37="C",0,IF(R37="D",-1,IF(R37="E",0,""))))))
A38: 253 | B38: 1 | C38: Hurricane Fiona (September 2022) | D38: Tropical Cyclone | E38: 20220917 | F38: 20220918 | G38: PR | H38: https://www.nytimes.com/2022/09/19/us/puerto-rico-power-hurricane-fiona.html | I38: On Anniversary of Hurricane Maria, Storm Leaves Puerto Rico in the ... | J38: Sep 20, 2022 ... And so, in the wake of Hurricane Fiona, most Puerto Ricans face the ... It is not forecast to approach the East Coast of the United States. | K38: Hurricane Fiona reminded residents that the agonizingly slow work of giving the island a stable power grid remained unfinished. SALINAS, P.R. — Hurricane Fiona deluged Puerto Rico with unrelenting rain and terrifying flash floods on Monday, forcing harrowing home rescues and making it difficult for power crews to reach many parts of the island. Now the island is once again in darkness, five years after Hurricane Maria inflicted more damage on Puerto Rico than any other disaster in recent history. While Fiona will be the direct culprit, Puerto Ricans will also blame years of power disruptions, the result of an agonizingly slow effort to finally give the island a stable grid. Hurricane Maria, a near-Category 5 storm, hit on Sept. 20, 2017, leaving about 3,000 dead and damaging 80 percent of the system. The last house was not reconnected to the system until nearly a year later. Hurricane Fiona, with far less ferocious winds, is the strongest storm to reach the island since. Its copious rains on Sunday and Monday — more than 30 inches in some areas in southern Puerto Rico and its central mountainous region — caused the island’s vast lattice of canals and creeks to swell, turned entire streets into muddy rivers and forced the rescues of more than 1,000 people. At least one person died, while operating a generator, while another death was recorded in the Dominican Republic. “I’ve never seen this in my life, not even in Maria,” said Ada Belmot Plaza, who had to be rescued by the Puerto Rico National Guard as waist-high floodwaters rose outside her daughter’s house in the El Coquí neighborhood of Salinas, on Puerto Rico’s southern coast. Some Puerto Ricans said Hurricane Fiona took them by surprise, and many in the hardest-hit areas were still waiting for government help on Monday as neighbors came together to clear fallen trees from roads and remove debris from homes. Gov. Pedro R. Pierluisi urged people to stay indoors. He said he expected most electricity to be back up “in a matter of days.” By Monday morning, power had been restored to some 100,000 customers, out of 1.5 million. The federal government paid $3.2 billion to patch up the island’s electrical grid in Hurricane Maria’s wake. But that was just to get the power back on; Congress earmarked an additional $10 billion to modernize the antiquated and inefficient system. The Puerto Rico government and the fiscal board appointed by Congress to oversee the island’s finances required that the power transmission and distribution system be privatized after deeming the Puerto Rico Electric Power Authority, which is bankrupt but continues to run power generation, to be ineffective. Funds from the Federal Emergency Management Agency will finance any new upgrades. In 2020, Puerto Rico awarded a 15-year contract to LUMA Energy, a private Canadian-American consortium, for a fixed annual fee of $115 million. After taking over in June of last year, the company quickly struggled with rolling summer blackouts. There was an islandwide outage in April, with no bad weather in sight. And so, in the wake of Hurricane Fiona, most Puerto Ricans face the daunting prospect of spoiled food and medication, sticky nights and the other familiar risks and indignities of being plunged into darkness. They are somewhat better equipped this time because those who could afford generators bought them after the Hurricane Maria fiasco. But that came with its own dangers: Officials on Monday said a man died while trying to operate a generator. His wife suffered severe burns, but survived. In the Dominican Republic, the storm killed at least one person, a 68-year-old man who was hit by a falling tree in the northern province of María Trinidad Sánchez, according to local media. As Hurricane Fiona moved westward, it battered the eastern provinces of the Dominican Republic, home to one of the largest tourism industries in the Caribbean. Heavy rain and 90-mile-per-hour winds set off mudslides that shuttered resorts and damaged highways, officials said. The storm is expected to pass near the islands of Turks and Caicos on Tuesday before strengthening at sea into a major hurricane — a Category 3 or higher — by Wednesday, the National Hurricane Center said. It is not forecast to approach the East Coast of the United States. In Puerto Rico, overflowing waterways and the loss of power caused pumps to fail, leaving 70 percent of households and businesses that rely on the public water and sewer system without potable water. Mr. Pierluisi said he had been coordinating with the White House to receive assistance. President Biden issued an emergency declaration on Sunday, unlocking federal funding and FEMA support. Mr. Biden called Mr. Pierluisi from Air Force One as the president flew back from the funeral of Queen Elizabeth II in London, according to the White House. States also lined up to send mutual aid. New York said more than 100 Spanish-speaking members of the State Police would help clear streets, direct traffic and respond to other needs in Puerto Rico. Most customers who had electricity on Monday, including a couple of hospitals, were in the San Juan metropolitan area, which was spared the worst of Hurricane Fiona’s rains. The damage from Fiona’s floodwaters is expected to be vast — in the “billions,” Mr. Pierluisi estimated — a sobering reminder that a storm’s categorization under the Saffir-Simpson scale considers its maximum wind speeds, but not its rainfall or storm surge potential. In the town of Cayey, residents had to clear out the mud after the La Plata River surged and almost completely submerged a two-story house. A temporary bridge erected over the Guaonica River in Utuado buckled, its demise captured on dramatic video as rushing waters and debris washed it away. The bridge was put up after Hurricane Maria to connect devastated neighborhoods in the area, and a new, permanent bridge was scheduled to go up in 2024. In Santa Isabel, on the southern coast of the island, Itzamary Alvarado said she had more water in her house than during Hurricane Maria. Government officials, she said, should have given the public more warning about Hurricane Fiona, which had initially approached the island as a tropical storm. “I think the government minimized what was going to happen,” Ms. Alvarado said. “I found out it was a hurricane at 11 a.m. on Sunday, so I left everything and ran to the supermarket. I had not prepared for a hurricane.” For her and many others, the storm was a test of whether the government response to disasters would be better after Maria. “We have been struggling for five years and see the same conditions from the government in the management of emergency situations,” Ms. Alvarado said. “It’s frustrating.” But she suddenly had a sign that things were changing for the better: Trucks from Puerto Rico’s power company, LUMA, appeared on her street. “A LUMA brigade just drove by my house,” she said. “I’ve never seen that before.” Comparisons to Hurricane Maria were inevitable, from both residents and officials. The island’s hospitals were running on backup generators, in stark contrast to 2017, when many lost power, damaging medical equipment and leaving hundreds of sick patients dangerously at risk. About 75 percent of cellphone towers were still functioning after the storm passed, compared with the near-total signal wipeout five years ago. Mr. Pierluisi stressed that officials were still in the rescue-and-response phase of the emergency and had not begun to assess the scale of the damage, or determine the island’s path to recovery. Still, he said, the local government’s response had so far been “exemplary” compared with what happened after Maria. “Maria served as a lesson, an exercise for our emergency response teams at all levels,” Mr. Pierluisi, a member of the pro-statehood New Progressive Party who took office in 2021, said in a news conference. “In terms of the coordination we’ve seen, there’s a big difference.” Hurricane Maria, which struck within weeks of Hurricane Irma in 2017, laid bare the tenuous state of the island’s aging, poorly maintained infrastructure. Its powerful winds, with gusts exceeding 100 m.p.h., destroyed thousands of homes and wiped out the island’s agriculture and access to communications. Recovery was painfully sluggish, and the lack of potable water, fuel and food supplies in the wake of the storm prompted an exodus of tens of thousands of residents to the United States mainland. Public fury bubbled up at the government’s response to the storm. In 2019, a grass-roots movement channeling the anger formed, fueling a popular uprising in 2019 that lasted 15 days and caused former Gov. Ricardo A. Rosselló to step down. Puerto Ricans remain skeptical of their leaders’ abilities to respond to disasters. In Salinas on Monday, Ana Medina Cardona, 74, said government reconstruction contractors had repaired a section of her tin roof that was torn apart by Hurricane Maria. On Sunday, rain started pouring through that repaired roof while she was home with her dog, Famy. “It seems they didn’t do a great job, because water was coming down the walls,” Ms. Medina Cardona said. “This time around, it was even worse than in Maria.” She waited in a shelter to hear if the water had receded enough for her to return home. But she was unconvinced it was her best option. “If we can go back,” she said, “that also means going back there to a house without power.” Reporting was contributed by Grace Ashford, Holga Enecia Pérez, Luis Ferré-Sadurní, Christine Hauser, Charo Henríquez, Anatoly Kurmanaev, Edgar Sandoval and Daniel Victor. Reporting was contributed by Grace Ashford, Holga Enecia Pérez, Luis Ferré-Sadurní, Christine Hauser, Charo Henríquez, Anatoly Kurmanaev, Edgar Sandoval and Daniel Victor. | N38: =IF(M38="","",IF(M38="A",1,IF(M38="B",0.5,IF(M38="C",0,IF(M38="D",-1,IF(M38="E",0,"")))))) | S38: =IF(R38="","",IF(R38="A",1,IF(R38="B",0.5,IF(R38="C",0,IF(R38="D",-1,IF(R38="E",0,""))))))
A39: 254 | B39: 3 | C39: Hurricane Ian (September 2022) | D39: Tropical Cyclone | E39: 20220928 | F39: 20220930 | G39: FL,SC | H39: https://dailyprogress.com/news/video_abae7172-3d41-59b2-ab88-bee3bba631ff.html | I39: Hurricane Ian's wind, rain start in Charleston - The Daily Progress | J39: Sep 30, 2022 ... A revived Hurricane Ian set its sights on South Carolina's coast Friday and the historic city of Charleston, with forecasters predicting a ... | K39: A revived Hurricane Ian set its sights on South Carolina's coast Friday and the historic city of Charleston, with forecasters predicting a storm surge and floods after the megastorm caused catastrophic damage in Florida and left people trapped in their homes. With all of South Carolina's coast under a hurricane warning, a steady stream of vehicles left Charleston on Thursday, many likely heeding officials' warnings to seek higher ground. Storefronts were sandbagged to ward off high water levels in an area prone to inundation. On Friday morning in Charleston, powerful wind gusts bent tree branches and sent sprays of steadily falling rain sideways. Streets in the 350-year-old city were largely empty, an ordinarily packed morning commute silenced by the advancing storm. City officials were pumping water from a storm drain over the sea wall, as water pooled in the streets and homes along the water were threatened. With winds holding at 85 mph (140 kph), the National Hurricane Center's update at 8 a.m. Friday placed Ian about 105 miles (175 km) southeast of Charleston and forecast a "life-threatening storm surge" and hurricane conditions along the Carolina coastal area later Friday. The hurricane warning stretched from the Savannah River to Cape Fear, with flooding likely across the Carolinas and southwestern Virginia, the center said. The forecast predicted a storm surge of up to 7 feet (2.1 meters) into coastal areas of the Carolinas, and rainfall of up to 8 inches (20 centimeters). | N39: =IF(M39="","",IF(M39="A",1,IF(M39="B",0.5,IF(M39="C",0,IF(M39="D",-1,IF(M39="E",0,"")))))) | S39: =IF(R39="","",IF(R39="A",1,IF(R39="B",0.5,IF(R39="C",0,IF(R39="D",-1,IF(R39="E",0,""))))))
A40: 255 | B40: 8 | C40: Hurricane Nicole (November 2022) | D40: Tropical Cyclone | E40: 20221110 | F40: 20221111 | G40: FL | H40: https://www.miamiherald.com/news/weather/hurricane/article268562187.html | I40: Hurricane Nicole leaves minor damage in Broward, Miami-Dade | J40: Nov 10, 2022 ... Hurricane Nicole wrecked two Broward piers and made a mess at the Hollywood Broadwalk ... United States · Cuba · Haiti · Venezuela · Americas. | K40: Nicole’s strong winds and drenching rain largely spared South Florida but there was some damage: Two popular Broward County fishing piers took a beating, the ocean briefly flooded Hollywood Beach’s ocean-side walkway and some shops, and a section of A1A in Fort Lauderdale was blocked by sand and flooding Thursday morning. Thousands also lost power, though the numbers were quickly declining. On Hollywood Beach, the sun was shining again Thursday morning but several inches of sand and debris coated sections of the Broadwalk. Fishing lures, stray flip-flops and uprooted marine plants dotted the sand, along with mounds of dirty gray sea foam. City staffers were already at work cleaning, using earth movers to scrape sand off the brick and dump it back on the beach. Others teamed up to right knocked-over stone trash cans and park benches. Business owners pressure-washed, mopped and swept the sand, sea foam — and in some cases, seawater — that made its way into their stores. “It’s amazing the ocean came right up. Thank God my awning made it,” said Frank Aubrey, owner of Little Venice Pizza, where the floor was littered with sand. The storm made landfall as a Category 1 hurricane just south of Vero Beach early Thursday, hitting the coast with strong winds and drenching the upper half of the state from Tampa to Cocoa Beach. In South Florida, gusts near the coast generally ranged between 35 and 45 miles an hour, with a few stronger gusts recorded in areas such as Dania Beach, and Juno Beach, said Robert Molleda, a severe weather expert with Miami’s National Weather Service office. Between 2 and 4 inches of rain generally fell in South Florida, with slightly higher totals in some parts of eastern Broward, he said. “From a rain and wind standpoint, it was not too bad,” Molleda said. “Coastal flooding was the biggest impact from the storm.” The most eye-catching damage from that flooding was at Anglin’s Pier in Lauderdale-by-the-Sea, where people can normally fish 24 hours a day. Waves took a chunk out of the middle of the nearly six-decade-old structure. No injuries were reported but nobody will be catching fish there for quite awhile. The pier has often been damaged by storms. It needed to be rebuilt after Hurricane Wilma in 2005, and needed renovations after Hurricane Irma in 2017, owner Spiro Marchelos said Thursday. “We’re fortunate that that’s the only damage that occurred, and we’re here to replace, fix and go on,” Marchelos said. “It’s going to take some time, but we’ll get it done.” Lauderdale-By-The-Sea Mayor Chris Vincent, in a statement on Thursday, called the pier an “iconic landmark” and “seeing it damaged is heartbreaking.” “While the pier is privately owned, I know our Town will do what we can to support the property owner in the coming days and months,” he said. Longtime Fort Lauderdale resident Tom Bradley was just outside Anglin’s on Thursday morning to see the damage to the pier. He noted that the high tide came in and damaged the middle of the pier. “It was bad here, but nowhere near as bad as it could’ve been if we were farther north because we were on the clean side of the storm, not the dirty side,” Bradley said. “There’s really not much damage here except for the pier.” There also was damage to the pier in Deerfield Beach, where city webcam footage showed violent swells jarred loose wooden railings and planks of the city’s pier. But the structure itself weathered Nicole’s pounding waves. Beach erosion was a concern across the coastline. In Miami Beach, which had been cleared and opened to visitors by Thursday afternoon, city officials were assessing erosion but so far had reported “no significant issues,” a spokeswoman said. In South Florida, where the effects of the winds were less pronounced, Nicole had also knocked out electricity to thousands — although by 10 a.m. on Thursday, only 550 customers in Broward remained without power, just 400 in Miami-Dade. One of those without power in Northeast Dade was Alexandra Quinan, 31, a law firm administrative assistant. The electricity at her and her husband’s house flicked off early Thursday evening — and was still out Friday morning. Her phone battery was nearly dead, but the night was not terrible. “I actually fell asleep pretty quickly. It was a cool night,” she said. “Breezy. Could have been worse.” | N40: =IF(M40="","",IF(M40="A",1,IF(M40="B",0.5,IF(M40="C",0,IF(M40="D",-1,IF(M40="E",0,"")))))) | S40: =IF(R40="","",IF(R40="A",1,IF(R40="B",0.5,IF(R40="C",0,IF(R40="D",-1,IF(R40="E",0,""))))))
A41: 255 | B41: 15 | C41: Hurricane Nicole (November 2022) | D41: Tropical Cyclone | E41: 20221110 | F41: 20221111 | G41: FL | H41: https://www.npr.org/2022/11/10/1135703897/hurricane-nicole-florida-georgia-south-carolina | I41: Nicole weakens to a tropical storm after reaching Florida's east coast | J41: Nov 10, 2022 ... ... Hurricane Nicole, Wednesday, Nov. 9, 2022, in Jensen Beach, Fla ... Tickets for the opening match of the United States at the World Cup have still ... | K41: Nicole was downgraded to a tropical storm Thursday morning, shortly after making landfall in Florida, according to the National Hurricane Center. As of 4 a.m. ET Thursday, Nicole was downgraded to tropical storm status, but it still packed maximum sustained winds of 70 miles per hour, the hurricane center said. It was moving west-northwest near 14 mph. Nicole made landfall just south of Vero Beach, hurricane center officials said. The east and west coasts of Florida, as well as the coasts of Georgia and South Carolina, are expected to have tropical storm conditions Thursday, causing storm surges and "large and damaging waves along the Atlantic coast," the NHC said. "Do not focus on the exact track of Nicole since it is a large storm with hazards extending well to the north of the center, outside of the forecast zone," the NHC said. The Appalachian Mountains could also experience some flooding Friday, which could extend all the way up to New York and Pennsylvania. Hurricane season in the Atlantic is typically a six-month period from June 1 to Nov. 30, and peaks between mid-August and late-October, according to the Florida Climate Center. Warnings were issued for many parts of Florida, including the southwestern Gulf coastline that was damaged by Hurricane Ian, a Category 4 storm Sept. 28. Many state residents are still recovering from the homes and crops destroyed destroyed by Ian. | N41: =IF(M41="","",IF(M41="A",1,IF(M41="B",0.5,IF(M41="C",0,IF(M41="D",-1,IF(M41="E",0,"")))))) | S41: =IF(R41="","",IF(R41="A",1,IF(R41="B",0.5,IF(R41="C",0,IF(R41="D",-1,IF(R41="E",0,""))))))
A42: 258 | B42: 3 | C42: Western/Central Drought and Heat Wave (2022) | D42: Drought | E42: 20220101 | F42: 20221231 | G42: AK,AZ,CA,CO,HI,IA,ID,IL,IN,KS,MI,MN,MO,MT,ND,NE,NM,NV,OH,OK,OR,SD,TX,UT,WA,WI,WY | H42: https://bismarcktribune.com/community/mandannews/news/article_ceee2f22-eb2b-11ec-85fb-07fee1000b80.html | I42: Rancher relief fund accepting applications; drought now nearly ... | J42: Jun 17, 2022 ... Jun 17, 2022 ... ICE detains Afghan man who escaped to West Fargo after fighting alongside US forces ... United States of America, US Virgin Islands ... | N42: =IF(M42="","",IF(M42="A",1,IF(M42="B",0.5,IF(M42="C",0,IF(M42="D",-1,IF(M42="E",0,"")))))) | S42: =IF(R42="","",IF(R42="A",1,IF(R42="B",0.5,IF(R42="C",0,IF(R42="D",-1,IF(R42="E",0,""))))))
A43: 258 | B43: 24 | C43: Western/Central Drought and Heat Wave (2022) | D43: Drought | E43: 20220101 | F43: 20221231 | G43: AK,AZ,CA,CO,HI,IA,ID,IL,IN,KS,MI,MN,MO,MT,ND,NE,NM,NV,OH,OK,OR,SD,TX,UT,WA,WI,WY | H43: https://bismarcktribune.com/news/national/article_99ba4378-9b2b-5fb2-90f0-821e81305436.html | I43: West dealing with heat wave; Indiana will tax loan forgiveness | Hot ... | J43: Sep 7, 2022 ... Sep 7, 2022; Sep 7, 2022 Updated Sep 7, 2022 ... A prolonged and unusual March heat wave is gripping cities across the West. ... United States of ... | N43: =IF(M43="","",IF(M43="A",1,IF(M43="B",0.5,IF(M43="C",0,IF(M43="D",-1,IF(M43="E",0,"")))))) | S43: =IF(R43="","",IF(R43="A",1,IF(R43="B",0.5,IF(R43="C",0,IF(R43="D",-1,IF(R43="E",0,""))))))
A44: 266 | B44: 1 | C44: Central and Southern Severe Weather (April 2023) | D44: Severe Storm | E44: 20230415 | F44: 20230415 | G44: AL,AR,FL,GA,IA,IL,IN,KS,KY,LA,MI,MN,MO,MS,NC,ND,NE,OH,OK,SC,SD,TN,TX,VA,WI | H44: https://www.cnn.com/2023/04/15/weather/severe-storms-southeast-midwest-hail-saturday | I44: Areas hit hard in recent weeks from tornadoes could face severe ... | J44: Apr 15, 2023 ... ... of the states that are expected to see potential hail storms this weekend. ... of the Ohio Valley and southern Great Lakes.” Another ... | K44: More than 50 million people are under the threat of severe storms Saturday from the Gulf Coast to the Great Lakes. Some of these same areas are still cleaning up from severe storms over the previous few weeks. "Severe thunderstorms capable of large to very large hail and damaging gusts are possible from the lower to mid Mississippi Valley westward into parts of the Ozarks, Ark-La-Tex and Sabine River Valley," the Storm Prediction Center said. A level 3 out of 5 "enhanced" risk for storms has been issued across parts of Missouri, Louisiana and Arkansas, including Little Rock, Arkansas, and St Louis. There's a level 2 of 5 "slight" risk for locations surrounding that enhanced risk zone, including Memphis, Tennessee; Shreveport, Louisiana; and Jackson, Mississippi. "Models are trending a little slower with the evolution of this storm system increasing the possibility of strong to possibly severe storms in advance of the associated cold front," the National Weather Service office in Little Rock said. The Little Rock weather service also emphasized that while the tornado threat is low, it cannot be discounted entirely, especially if any super cells develop. Arkansas and Mississippi were each hit by an EF-4 tornado just weeks ago. Many still have tarps covering their roofs, and have yet to finish clearing up debris and damage to businesses. Now, new storms are set to arrive in many of these hard-hit areas this weekend. Hail the size of tennis balls Hailstones larger than golf balls, and possibly even the size of tennis balls may fall in this region Saturday afternoon and evening. The large hail threat will be focused across portions of Arkansas, Missouri, Louisiana and east Texas. While not as deadly as tornadoes, hail can still cause significant damage to vehicles, homes, crops and livestock. Even small hailstones can have an impact when there's enough volume. "When hail builds up, it can cause a loss of power, bring down trees and cause flash floods and mudslides in steep areas," the International Federation of the Red Cross states on its disasters and preparation website. In 2022, there were over 4,400 major hailstorms reported in NOAA's severe storms database. According to the Insurance Information Institute, hail-related insured losses between averaged between $8 billion to $14 billion a year in the last two decades. Texas was the state with the most hail claims paid for auto and home insurance followed by Illinois, Minnesota, and Missouri -- three of the states that are expected to see potential hail storms this weekend. These storms are associated with a low pressure system that will track eastward, from the central Plains, slowly toward the Mid-Mississippi River Valley and Great Lakes by Sunday. These strong thunderstorms are forecast to develop quickly ahead of the cold front during the early to mid-afternoon. They are expected to move out of Arkansas and Missouri by midnight and continue to race eastward through the overnight hours. Flash flooding is also possible across this region on Saturday, as 1 to 3 inches of rain is forecast on top of already saturated soils. "Some of this region has had recent rains, and are 150 to 600 percent of normal," the Weather Prediction Center said. "These sensitive soils could quickly become over saturated and lead to isolated/scattered areas of flooding." Threat pushes east Sunday This system will push eastward on Sunday bringing rain to the Ohio Valley and the potential for severe storms across the Southeast. "Isolated severe thunderstorms, associated with wind-damage and hail, will be possible on Sunday in parts of the Southeast," the Storm Prediction Center said. "Marginally severe storms will be possible further north into parts of the Ohio Valley and southern Great Lakes." Another concern: more rainfall across South Florida, which is cleaning up from record flooding Wednesday. "Some of the area is still susceptible/vulnerable due to recent rainfall so this additional threat of heavy rainfall may lead to flash flooding over the urbanized corridor of southeast Florida," the Weather Prediction Center said Saturday morning. Rain showers are expected for Miami and Fort Lauderdale from Sunday night through Monday. | N44: =IF(M44="","",IF(M44="A",1,IF(M44="B",0.5,IF(M44="C",0,IF(M44="D",-1,IF(M44="E",0,"")))))) | S44: =IF(R44="","",IF(R44="A",1,IF(R44="B",0.5,IF(R44="C",0,IF(R44="D",-1,IF(R44="E",0,""))))))
A45: 274 | B45: 3 | C45: Central and Southern Severe Weather (June 2023) | D45: Severe Storm | E45: 20230615 | F45: 20230618 | G45: AL,AR,FL,GA,IA,IL,IN,KS,KY,LA,MI,MN,MO,MS,NC,ND,NE,OH,OK,SC,SD,TN,TX,VA,WI | H45: https://dailyprogress.com/news/nation-world/article_167231db-bb8a-51fe-9bd4-87b137f829bd.html | I45: Deadly tornado strikes Texas Panhandle; historic start at U.S. Open ... | J45: Jun 20, 2023 ... Watch Ukrainian police save a woman buried alive under rubble after a Russian missile strike, why 2023 has become the second deadliest year on ... | N45: =IF(M45="","",IF(M45="A",1,IF(M45="B",0.5,IF(M45="C",0,IF(M45="D",-1,IF(M45="E",0,"")))))) | S45: =IF(R45="","",IF(R45="A",1,IF(R45="B",0.5,IF(R45="C",0,IF(R45="D",-1,IF(R45="E",0,""))))))
A46: 283 | B46: 6 | C46: Hurricane Idalia (August 2023) | D46: Tropical Cyclone | E46: 20230829 | F46: 20230831 | G46: FL,GA,NC,SC | H46: https://www.news-journalonline.com/story/weather/hurricane/2023/08/31/national-hurricane-center-two-week-forecast-for-florida-jose-idalia-franklin-peak-period/70727772007/ | I46: Hurricane forecast for Florida: Jose, Idalia, Franklin. What's next? | J46: Aug 31, 2023 ... ... Hurricane Idalia and its aftermath from journalists across the USA TODAY network ... 2023 disaster preparedness sales tax holiday. The ... | N46: =IF(M46="","",IF(M46="A",1,IF(M46="B",0.5,IF(M46="C",0,IF(M46="D",-1,IF(M46="E",0,"")))))) | S46: =IF(R46="","",IF(R46="A",1,IF(R46="B",0.5,IF(R46="C",0,IF(R46="D",-1,IF(R46="E",0,""))))))
